Workbook
Name AcucarNY2010: #REF!
Name AcucarSP2010: #REF!
Name AcucarSP2010Defl: Cana!AcucarSP2010*#REF!
Name AcucarSP2010USD: #REF!/#REF!
Name AcucarSP2015: #REF!
Name Argentina1990: #REF!
Name Argentina2000: #REF!
Name Argentina2010: #REF!
Name Argentina2015: #REF!
Name AtacadoSP1995Defl: #REF!*#REF!
Name Beef2010: #REF!
Name BezerroMS2000Defl: #REF!*#REF!
Name BoiSP2000Defl: #REF!*#REF!
Name BoiSP2010: #REF!
Name BoiSP2010Defl: #REF!*#REF!
Name BoiSP2010DeflKg: #REF!*#REF!/30
Name BoiSP2010USD: #REF!/#REF!
Name BoiSPEvolPrecos: #REF!
Name BrentOil2000: #REF!
Name BrentOil2010: #REF!
Name CafeArabSP1995: #REF!
Name CafeArabSP1995Defl: 'Demais AGRÍCOLAS'!CafeArabSP1995*#REF!
Name CafeArabSP2010: #REF!
Name CafeArabSP2010Defl: #REF!*#REF!
Name CafeArabSP2010USD: #REF!/#REF!
Name CafeDifArabRobu2010: 'Demais AGRÍCOLAS'!CafeArabSP2010-'Demais AGRÍCOLAS'!CafeRobuSP2010
Name CafeNY2010: #REF!
Name CafeRobuSP2010: #REF!
Name CafeRobuSP2010USD: #REF!/#REF!
Name CafeRobustaSP2010Defl: #REF!*#REF!
Name CafeRobustaSP2010USD: #REF!/#REF!
Name CanaSP2010Defl: #REF!*#REF!
Name CanaSP2010USD: #REF!/#REF!
Name CarnesEvol: 'PECUÁRIA Charts'!$R$18:$U$22
Name CBOT1990ton: #REF!*39.37
Name CBOT1990USD: #REF!/100
Name CBOT1990USDsaca: #REF!/45.36
Name CBOT1990USDton: #REF!*0.367437
Name CBOT2000bu: #REF!
Name CBOT2000PlusPremium: Soja!CBOT2000USD+Soja!PremioPR2000
Name CBOT2000USD: ROUND(#REF!/100,2)
Name CBOT2010bu: #REF!
Name CBOT2010USDsaca: #REF!/45.36
Name CBOT2010USDton: #REF!*0.367437
Name ChickenMeat2010: #REF!
Name Cotlook2010: #REF!
Name Cotlook2015: #REF!
Name Culturas: {"Soja";"Trigo"}
Name DDG_MT2020: #REF!
Name DDG_MT2020Defl: #REF!*#REF!
Name DDG_MT2020USD: #REF!/#REF!
Name desde1990: #REF!
Name desde1995: #REF!
Name desde2000: #REF!
Name desde2010: #REF!
Name desde2013: #REF!
Name desde2015: #REF!
Name desde2020: #REF!
Name ESALQ2000Arroba: #REF!*33.11258
Name ESALQ2000centsLB: #REF!*100/#REF!

Sheet Capa
U4: Data de atualização: | V4: 46296
B24: instagram.com/carloscogo
B25: www.carloscogo.com.br
B26: consultoria@carloscogo.com.br
B27: +55 51 3248 1117 | +55 51 999 867 666

Sheet Evolução de Preços
A3: COMMODITY | B3: AÇÚCAR | C3: AÇÚCAR | D3: ALGODÃO | E3: ALGODÃO | F3: ALGODÃO | G3: ARROZ | H3: ARROZ | I3: ARROZ T1 | J3: ARROZ T1 | K3: ARROZ 100B | L3: ARROZ US/4 | M3: CAFÉ | N3: CAFÉ | O3: CAFÉ | P3: CANA | Q3: ETANOL | R3: ETANOL | S3: FEIJÃO | T3: LARANJA | U3: LARANJA | V3: MILHO | W3: MILHO | X3: MILHO | Y3: MILHO | Z3: MILHO | AA3: MILHO | AB3: MILHO | AC3: MILHO | AD3: MILHO | AE3: MILHO | AF3: DDG MILHO | AG3: SOJA | AH3: SOJA | AI3: SOJA | AJ3: SOJA | AK3: SOJA | AL3: SOJA | AM3: FARELO SOJA | AN3: FARELO SOJA | AO3: ÓLEO SOJA | AP3: OLEO SOJA | AQ3: SORGO | AR3: TRIGO | AS3: TRIGO | AT3: TRIGO | AU3: TRIGO | AV3: TRIGO | AW3: BEZERRO | AX3: BOI GORDO | AY3: BEEF | AZ3: FRANGO | BA3: FRANGO | BB3: CHICKEN MEAT | BC3: LEITE | BD3: LEITE | BE3: LEITE | BF3: LEITE | BG3: LEITE | BH3: LEITE | BI3: LEITE | BJ3: SUÍNO | BK3: SUÍNO | BL3: OVOS | BM3: TILÁPIA | BN3: BRENT | BO3: NATURAL GAS | BP3: DIESEL S-10 | BQ3: E. HIDRATADO | BR3: GASOLINA C | BS3: Food | BT3: Meat | BU3: Dairy | BV3: Cereals | BW3: Oils | BX3: Sugar | BY3: DÓLAR
A4: REFERÊNCIA | B4: ATACADO | C4: ICE NY | D4: ICE US | E4: COTLOOK 'A' | F4: ESALQ | G4: RS | H4: MT | I4: ATACADO SP | J4: VAREJO SP | K4: TAILÂNDIA | L4: EUA | M4: ARÁBICA SP | N4: ICE US | O4: CONILON SP | P4: SP | Q4: ANIDRO | R4: HIDRATADO | S4: CORES - SP | T4: INDÚSTRIA SP | U4: MESA SP | V4: ATACADO SP | W4: GO | X4: MS | Y4: MT | Z4: PR | AA4: RS | AB4: CBOT | AC4: GOLFO EUA | AD4: ARGENTINA | AE4: PARANAGUÁ | AF4: 32% PB - MT | AG4: MT | AH4: PR | AI4: PARANAGUÁ | AJ4: RS | AK4: CHICAGO | AL4: PRÊMIO | AM4: ATACADO SP | AN4: CHICAGO | AO4: ATACADO SP | AP4: CHICAGO | AQ4: GO | AR4: PR | AS4: RS | AT4: ARGENTINA | AU4: US SRW | AV4: US HRW | AW4: MS | AX4: SP | AY4: World Bank | AZ4: VIVO SP | BA4: RESFRIADO SP | BB4: World Bank | BC4: BRASIL | BD4: GO | BE4: MG | BF4: PR | BG4: RS | BH4: SC | BI4: SP | BJ4: VIVO SC | BK4: CARCAÇA | BL4: BRANCOS SP | BM4: NORTE PR | BN4: GLOBAL | BO4: EUROPE | BP4: VAREJO BR | BQ4: VAREJO BR | BR4: VAREJO BR | BS4: FAO | BT4: FAO | BU4: FAO | BV4: FAO | BW4: FAO | BX4: FAO | BY4: COMERCIAL
A5: UNIDADE | B5: R$/50 kg | C5: ¢/lb | D5: ¢/lb | E5: ¢/lb | F5: R$/lb | G5: R$/50 kg | H5: R$/60 kg | I5: R$/30 kg | J5: R$/kg | K5: US$/t | L5: US$/t | M5: R$/60 kg | N5: ¢/lb | O5: R$/60 kg | P5: R$/t | Q5: R$/l | R5: R$/l | S5: R$/60 kg | T5: R$/40,8 kg | U5: R$/40,8 kg | V5: R$/60 kg | W5: R$/60 kg | X5: R$/60 kg | Y5: R$/60 kg | Z5: R$/60 kg | AA5: R$/60 kg | AB5: US$/bu | AC5: US$/t | AD5: US$/t | AE5: US$/t | AF5: R$/t | AG5: R$/60 kg | AH5: R$/60 kg | AI5: R$/60 kg | AJ5: R$/60 kg | AK5: ¢/bushel | AL5: US$/bu | AM5: R$/t | AN5: US$/t | AO5: R$/t | AP5: US$/t | AQ5: R$/60 kg | AR5: R$/60 kg | AS5: R$/60 kg | AT5: US$/t | AU5: US$/t | AV5: US$/t | AW5: R$/un | AX5: R$/@ 30 DIAS | AY5: US$/kg | AZ5: R$/kg vivo | BA5: R$/kg | BB5: US$/kg | BC5: R$/l | BD5: R$/l | BE5: R$/l | BF5: R$/l | BG5: R$/l | BH5: R$/l | BI5: R$/l | BJ5: R$/kg vivo | BK5: R$/kg | BL5: R$/CX 30 DZ | BM5: R$/kg | BN5: US$/barril | BO5: US$/mmbtu | BP5: R$/l | BQ5: R$/l | BR5: R$/l | BS5: Price Index | BT5: Price Index | BU5: Price Index | BV5: Price Index | BW5: Price Index | BX5: Price Index | BY5: VENDA
A6: ÚLTIMOS 30 DIAS | B6: 0.090695361 | C6: -0.027322404 | D6: -0.11395477 | E6: -0.046286877 | F6: -0.023270872 | G6: 0.059609455 | H6: 0 | I6: 0 | J6: 0 | K6: 0.032967033 | L6: 0.018181818 | M6: -0.11731138 | N6: -0.18479988 | O6: -0.067698206 | P6: -0.01371376 | Q6: 0 | R6: 0.14419924 | S6: 0.15954633 | T6: -0.059332906 | U6: -0.0070762303 | V6: 0.0086893555 | W6: 0 | X6: 0.066666667 | Y6: 0.031578947 | Z6: 0.032786885 | AA6: 0.014925373 | AB6: 0.035276825 | AC6: 0.0084638345 | AD6: 0.0045045045 | AE6: -0.035644637 | AF6: 0.022920204 | AG6: 0.048689139 | AH6: 0.034649152 | AI6: 0.038374718 | AJ6: 0.055172414 | AK6: 0.049741345 | AL6: -0.125 | AM6: 0.14298772 | AN6: 0.13901863 | AO6: 0.029752003 | AP6: -0.015735793 | AQ6: 0 | AR6: 0.023382697 | AS6: 0.05518131 | AT6: 0.047808765 | AU6: 0.13358663 | AV6: 0.032181818 | AW6: 0.0054213755 | AX6: 0.041509434 | AY6: -0.0041208791 | AZ6: 0.0042194093 | BA6: 0.12735166 | BB6: -0.0059171598 | BC6: 0 | BD6: 0 | BE6: 0 | BF6: 0 | BG6: 0 | BH6: 0 | BI6: 0 | BJ6: 0.10805085 | BK6: 0.11653117 | BL6: 0.016839378 | BM6: 0 | BN6: 0.16298774 | BO6: 0.0042633823 | BP6: 0.063860668 | BQ6: 0.04859335 | BR6: 0.004601227 | BS6: 0 | BT6: 0 | BU6: 0 | BV6: 0 | BW6: 0 | BX6: 0 | BY6: 0.007751938
A7: EM 2026 | B7: 0.1298239 | C7: 0.20596206 | D7: 0.23455272 | E7: 0.2746431 | F7: 0.18261654 | G7: 0.54775755 | H7: 0.6 | I7: -0.037469921 | J7: 0.014285714 | K7: 0.18987342 | L7: -0.0088495575 | M7: -0.31250615 | N7: -0.24541929 | O7: -0.24744903 | P7: -0.19410393 | Q7: -0.25955921 | R7: -0.15065789 | S7: 0.52121291 | T7: -0.20793951 | U7: -0.27227723 | V7: 0.0075220599 | W7: 0 | X7: -0.01754386 | Y7: -0.08411215 | Z7: -0.0078740157 | AA7: 0.014925373 | AB7: 0.18975225 | AC7: 0.13910955 | AD7: 0.0045045045 | AE7: 0.0054712893 | AF7: 0.082095584 | AG7: 0.30841121 | AH7: 0.18199219 | AI7: 0.19515997 | AJ7: 0.15909091 | AK7: 0.26583493 | AL7: -0.58210204 | AM7: 0.23447136 | AN7: 0.27621979 | AO7: 0.070178654 | AP7: 0.36592455 | AQ7: 0.076053685 | AR7: 0.10826004 | AS7: 0.17687682 | AT7: 0.2705314 | AU7: 0.37050988 | AV7: 0.36302521 | AW7: 0.12053797 | AX7: 0.11245466 | AY7: -0.09033877 | AZ7: -0.13296903 | BA7: 0.001285347 | BB7: -0.04 | BC7: 0.42461417 | BD7: 0.53204794 | BE7: 0.4636747 | BF7: 0.42471137 | BG7: 0.32734531 | BH7: 0.42492339 | BI7: 0.41052432 | BJ7: -0.37214886 | BK7: -0.36074476 | BL7: 0.23488349 | BM7: -0.0039177277 | BN7: 0.56237831 | BO7: 0.80272109 | BP7: 0.20757825 | BQ7: -0.086859688 | BR7: 0.053054662 | BS7: 0.07380003 | BT7: 0.023792595 | BU7: -0.014152134 | BV7: 0.081676858 | BW7: 0.16726372 | BX7: 0.18423268 | BY7: -0.033457249
A8: 12 MESES | B8: 0.018405944 | C8: 0.12944162 | D8: 0.21182861 | E8: 0.19961612 | F8: 0.15277236 | G8: 0.35346242 | H8: 0.34265734 | I8: -0.17671273 | J8: -0.079913607 | K8: 0.32394366 | L8: -0.066666667 | M8: -0.27503205 | N8: -0.2403393 | O8: -0.26083698 | P8: -0.30802015 | Q8: -0.20496894 | R8: -0.061090909 | S8: 0.38555455 | T8: -0.4134 | U8: -0.48082745 | V8: 0.082193909 | W8: 0.094339623 | X8: 0.018181818 | Y8: 0.042553191 | Z8: 0.05 | AA8: -0.028571429 | AB8: 0.24075161 | AC8: 0.19392003 | AD8: 0.115 | AE8: 0.04974359 | AF8: 0.070559178 | AG8: 0.19148936 | AH8: 0.20336737 | AI8: 0.20230005 | AJ8: 0.18604651 | AK8: 0.30303779 | AL8: -0.80556136 | AM8: 0.3725466 | AN8: 0.40022967 | AO8: -0.072723784 | AP8: 0.34559581 | AQ8: 0 | AR8: 0.027362425 | AS8: -0.0017979027 | AT8: 0.1793722 | AU8: 0.44164014 | AV8: 0.45713552 | AW8: 0.17346783 | AX8: 0.1737765 | AY8: 0.050609071 | AZ8: -0.13924051 | BA8: -0.044171779 | BB8: -0.036569085 | BC8: 0.18032787 | BD8: 0.25641026 | BE8: 0.19367589 | BF8: 0.17886179 | BG8: 0.12711864 | BH8: 0.19230769 | BI8: 0.16015625 | BJ8: -0.36759371 | BK8: -0.3785822 | BL8: -0.13943131 | BM8: 0 | BN8: 0.50273696 | BO8: 0.90710675 | BP8: 0.20957096 | BQ8: -0.044289044 | BR8: 0.056451613 | BS8: 0.036710952 | BT8: 0.0002240848 | BU8: -0.18984027 | BV8: 0.10944126 | BW8: 0.17228415 | BX8: 0.070397006 | BY8: -0.026217228
A9: 24 MESES | B9: -0.145327 | C9: -0.23407917 | D9: 0.10435859 | E9: 0.10424028 | F9: 0.05665474 | G9: -0.30584077 | H9: -0.30434783 | I9: -0.42118863 | J9: -0.3014103 | K9: 0 | L9: -0.27272727 | M9: 0.044519362 | N9: 0.11922238 | O9: -0.36377466 | P9: -0.26370757 | Q9: -0.096746877 | R9: 0.052846191 | S9: 0.44148477 | T9: -0.65400495 | U9: -0.73179844 | V9: 0.11261981 | W9: 0.035714286 | X9: -0.0088495575 | Y9: 0.11363636 | Z9: 0.024390244 | AA9: 0.014925373 | AB9: 0.23350846 | AC9: 0.16394526 | AD9: 0.082524272 | AE9: 0.11104991 | AF9: 0.075067359 | AG9: 0.085271318 | AH9: 0.12974753 | AI9: 0.15082202 | AJ9: 0.15037594 | AK9: 0.26099426 | AL9: -0.78362316 | AM9: 0.068291926 | AN9: 0.13010767 | AO9: 0.10263536 | AP9: 0.49764524 | AQ9: 0 | AR9: -0.11353663 | AS9: -0.10032995 | AT9: 0.069105691 | AU9: 0.36109794 | AV9: 0.26300567 | AW9: 0.65272026 | AX9: 0.39296529 | AY9: 0.151517 | AZ9: -0.10018904 | BA9: 0.04144385 | BB9: 0.1562086 | BC9: 0.0049900548 | BD9: 0.046524045 | BE9: 0.0091221973 | BF9: -0.0061004867 | BG9: -0.02133922 | BH9: -0.005702067 | BI9: 0.045038705 | BJ9: -0.37663886 | BK9: -0.36858238 | BL9: 0.032300485 | BM9: 0 | BN9: 0.34398351 | BO9: 0.79900999 | BP9: 0.21963394 | BQ9: 0.014851485 | BR9: 0.07907743 | BS9: 0.060607028 | BT9: 0.057616745 | BU9: -0.13426386 | BV9: 0.014974318 | BW9: 0.37089094 | BX9: -0.16461539 | BY9: -0.045521292

Sheet Evolução Charts

Sheet Algodão
C4: Algodão | D4: Algodão | E4: Algodão | F4: Algodão | G4: Algodão | H4: Algodão | I4: Algodão
A5: Ano | B5: Mês | C5: Indicador Esalq | D5: Indicador Esalq | E5: Indicador Esalq | F5: Indicador Esalq | G5: Indicador Esalq | H5: Futuro NY ICE | I5: Cotlook A Index
C6: R$/libra-peso | D6: ¢/libra-peso | E6: R$/@ | F6: US$/@ | G6: Deflacionado | H6: ¢/libra-peso | I6: ¢/libra-peso
A7: 1990 | B7: JAN
B8: FEV
B9: MAR
B10: ABR
B11: MAI
B12: JUN
B13: JUL
B14: AGO
B15: SET
B16: OUT
B17: NOV
B18: DEZ
A19: 1991 | B19: JAN
B20: FEV
B21: MAR
B22: ABR
B23: MAI
B24: JUN
B25: JUL
B26: AGO
B27: SET
B28: OUT
B29: NOV
B30: DEZ
A31: 1992 | B31: JAN
B32: FEV
B33: MAR
B34: ABR
B35: MAI
B36: JUN
B37: JUL
B38: AGO
B39: SET
B40: OUT
B41: NOV
B42: DEZ
A43: 1993 | B43: JAN
B44: FEV
B45: MAR
B46: ABR
B47: MAI
B48: JUN
B49: JUL
B50: AGO
B51: SET
B52: OUT
B53: NOV
B54: DEZ
A55: 1994 | B55: JAN
B56: FEV
B57: MAR
B58: ABR
B59: MAI
B60: JUN
B61: JUL
B62: AGO
B63: SET
B64: OUT
B65: NOV
B66: DEZ
A67: 1995 | B67: JAN
B68: FEV
B69: MAR
B70: ABR
B71: MAI
B72: JUN
B73: JUL
B74: AGO
B75: SET
B76: OUT
B77: NOV
B78: DEZ
A79: 1996 | B79: JAN
B80: FEV
B81: MAR
B82: ABR
B83: MAI
B84: JUN
B85: JUL
B86: AGO
B87: SET
B88: OUT
B89: NOV
B90: DEZ
A91: 1997 | B91: JAN
B92: FEV
B93: MAR
B94: ABR
B95: MAI
B96: JUN
B97: JUL
B98: AGO
B99: SET
B100: OUT
B101: NOV
B102: DEZ
A103: 1998 | B103: JAN
...

Sheet Algodão Charts

Sheet Arroz
C4: Arroz em casca | D4: Arroz em casca | E4: Arroz em casca | F4: Arroz em casca | G4: Arroz em casca | H4: Arroz Beneficiado | I4: Arroz Beneficiado | J4: Arroz Beneficiado | K4: Arroz Beneficiado | L4: Arroz Beneficiado | M4: Arroz Beneficiado | N4: Arroz Beneficiado | O4: Arroz Beneficiado
A5: Ano | B5: Mês | C5: RS | D5: RS | E5: RS | F5: MT | G5: MT | H5: Atacado SP - T1 | I5: Atacado SP - T1 | J5: Atacado SP - T1 | K5: Varejo SP - T1 | L5: Varejo SP - T1 | M5: Varejo SP - T1 | N5: Tailândia WR100B | O5: EUA US/4
C6: R$/50 kg | D6: US$/50 kg | E6: Deflacionado | F6: R$/60 kg | G6: US$/60 kg | H6: R$/30 kg | I6: US$/30 kg | J6: Deflacionado | K6: R$/kg | L6: US$/kg | M6: Deflacionado | N6: US$/t FOB | O6: US$/t FOB
A7: 1990 | B7: JAN | C7: 136 | D7: 9.5011876 | F7: 140.9929 | G7: 9.85 | H7: 606 | I7: 42.336174 | K7: 15.2 | L7: 1.0618974 | N7: 301.59 | O7: 338
B8: FEV | C8: 265 | D8: 11.199865 | F8: 282.03912 | G8: 11.92 | H8: 613.75 | I8: 25.939309 | K8: 27.13 | L8: 1.1466126 | N8: 300 | O8: 356
B9: MAR | C9: 316.5 | D9: 8.3849944 | F9: 414.45108 | G9: 10.98 | H9: 828 | I9: 21.936099 | K9: 30.63 | L9: 0.81147671 | N9: 297.27 | O9: 348
B10: ABR | C10: 374 | D10: 7.8216497 | F10: 435.1256 | G10: 9.1 | H10: 890 | I10: 18.613017 | K10: 29.28 | L10: 0.61234733 | N10: 288.25 | O10: 342
B11: MAI | C11: 476.5 | D11: 9.1278279 | F11: 541.86714 | G11: 10.38 | H11: 920 | I11: 17.623508 | K11: 30.4 | L11: 0.58234201 | N11: 280 | O11: 338
B12: JUN | C12: 567 | D12: 9.9176156 | F12: 701.48817 | G12: 12.27 | H12: 990 | I12: 17.316472 | K12: 30.5 | L12: 0.53348726 | N12: 270.48 | O12: 336
B13: JUL | C13: 584.5 | D13: 8.7745635 | F13: 835.32702 | G13: 12.54 | H13: 1413.75 | I13: 21.223335 | K13: 33.13 | L13: 0.49735037 | N13: 258.41 | O13: 333
B14: AGO | C14: 621 | D14: 8.6560174 | F14: 859.46916 | G14: 11.98 | H14: 2157 | I14: 30.06607 | K14: 34 | L14: 0.47392044 | N14: 255 | O14: 306
B15: SET | C15: 808 | D15: 10.659209 | F15: 924.03857 | G15: 12.19 | H15: 3062.5 | I15: 40.400776 | K15: 40.88 | L15: 0.53929264 | N15: 251.25 | O15: 287
B16: OUT | C16: 1068 | D16: 11.189925 | F16: 983.0629 | G16: 10.3 | H16: 3075 | I16: 32.218183 | K16: 66 | L16: 0.69151221 | N16: 255 | O16: 284
B17: NOV | C17: 1514 | D17: 12.422054 | F17: 1193.2052 | G17: 9.79 | H17: 4766 | I17: 39.104037 | K17: 101.25 | L17: 0.83073515 | N17: 260 | O17: 314
B18: DEZ | C18: 1997.5 | D18: 12.844338 | F18: 1702.9002 | G18: 10.95 | H18: 5600 | I18: 36.009157 | K18: 122.5 | L18: 0.7877003 | N18: 260 | O18: 325
A19: 1991 | B19: JAN | C19: 2266.5 | D19: 10.295721 | F19: 2031.8922 | G19: 9.23 | H19: 5450 | I19: 24.756973 | K19: 170 | L19: 0.77223585 | N19: 310 | O19: 333
B20: FEV | C20: 3634.5 | D20: 16.26684 | F20: 2683.3943 | G20: 12.01 | H20: 5000 | I20: 22.378374 | K20: 210.75 | L20: 0.94324844 | N20: 353 | O20: 349
B21: MAR | C21: 3819 | D21: 15.983761 | F21: 2946.0069 | G21: 12.33 | H21: 5430 | I21: 22.726322 | K21: 211 | L21: 0.88310384 | N21: 348 | O21: 364
B22: ABR | C22: 5561 | D22: 21.328577 | F22: 3136.5819 | G22: 12.03 | H22: 5400 | I22: 20.71108 | K22: 209.5 | L22: 0.80351321 | N22: 318 | O22: 372
B23: MAI | C23: 3850.8333 | D23: 13.525934 | F23: 3174.405 | G23: 11.15 | H23: 5385 | I23: 18.914647 | K23: 220.6 | L23: 0.77485072 | N23: 320 | O23: 380
B24: JUN | C24: 3819.5 | D24: 12.232969 | F24: 3209.7244 | G24: 10.28 | H24: 6525 | I24: 20.898056 | K24: 221.75 | L24: 0.71021362 | N24: 303 | O24: 389
B25: JUL | C25: 3801 | D25: 10.967481 | F25: 3261.2237 | G25: 9.41 | H25: 7912.5 | I25: 22.830886 | K25: 225 | L25: 0.64921949 | N25: 310 | O25: 383
B26: AGO | C26: 4348.5 | D26: 11.596 | F26: 3435 | G26: 9.16 | H26: 11360 | I26: 30.293333 | K26: 254.25 | L26: 0.678 | N26: 325 | O26: 369
B27: SET | C27: 5284.5 | D27: 12.010227 | F27: 4012.8 | G27: 9.12 | H27: 12500 | I27: 28.409091 | K27: 273.38 | L27: 0.62131818 | N27: 325 | O27: 378
B28: OUT | C28: 7727.5 | D28: 12.879167 | F28: 5088 | G28: 8.48 | H28: 13437.5 | I28: 22.395833 | K28: 423 | L28: 0.705 | N28: 300 | O28: 383
B29: NOV | C29: 8707.5 | D29: 11.533113 | F29: 7081.9 | G29: 9.38 | H29: 17600 | I29: 23.311258 | K29: 540 | L29: 0.71523179 | N29: 300 | O29: 386
B30: DEZ | C30: 9216 | D30: 9.4233129 | F30: 8361.9 | G30: 8.55 | H30: 17600 | I30: 17.99591 | K30: 608.75 | L30: 0.62244376 | N30: 305 | O30: 386
A31: 1992 | B31: JAN | C31: 9664 | D31: 8.0735171 | F31: 10066.77 | G31: 8.41 | H31: 17600 | I31: 14.703425 | K31: 664 | L31: 0.55472013 | N31: 300 | O31: 380
B32: FEV | C32: 13266.5 | D32: 9.0003392 | F32: 11570.9 | G32: 7.85 | H32: 19375 | I32: 13.144505 | K32: 821.25 | L32: 0.55715739 | N32: 300 | O32: 372
B33: MAR | C33: 13618 | D33: 7.5113072 | F33: 13343.68 | G33: 7.36 | H33: 20680 | I33: 11.406509 | K33: 791.88 | L33: 0.43677882 | N33: 300 | O33: 365
B34: ABR | C34: 14896 | D34: 6.7189896 | F34: 14898.24 | G34: 6.72 | H34: 23500 | I34: 10.59991 | K34: 907.5 | L34: 0.40933694 | N34: 305 | O34: 360
B35: MAI | C35: 19057 | D35: 7.3296154 | F35: 17706 | G35: 6.81 | H35: 31000 | I35: 11.923077 | K35: 1082.5 | L35: 0.41634615 | N35: 300 | O35: 340
B36: JUN | C36: 26601.5 | D36: 7.8239706 | F36: 19958 | G36: 5.87 | H36: 39250 | I36: 11.544118 | K36: 1485 | L36: 0.43676471 | N36: 305 | O36: 323
B37: JUL | C37: 28376.5 | D37: 7.3705195 | F37: 26911.5 | G37: 6.99 | H37: 44700 | I37: 11.61039 | K37: 1804 | L37: 0.46857143 | N37: 305 | O37: 320
B38: AGO | C38: 40500 | D38: 8.7096774 | F38: 37479 | G38: 8.06 | H38: 63500 | I38: 13.655914 | K38: 2203.75 | L38: 0.47392473 | N38: 305 | O38: 330
B39: SET | C39: 56150 | D39: 9.7516499 | F39: 46754.96 | G39: 8.12 | H39: 86800 | I39: 15.074679 | K39: 3173.8 | L39: 0.55119833 | N39: 300 | O39: 327
B40: OUT | C40: 64900 | D40: 8.8298118 | F40: 66003.898 | G40: 8.98 | H40: 106750 | I40: 14.523612 | K40: 4040.75 | L40: 0.54975443 | N40: 290 | O40: 329
B41: NOV | C41: 75150 | D41: 8.4701825 | F41: 88101.939 | G41: 9.93 | H41: 133000 | I41: 14.990476 | K41: 4870.75 | L41: 0.54898392 | N41: 285 | O41: 326
B42: DEZ | C42: 103400 | D42: 9.3542492 | F42: 111643.38 | G42: 10.1 | H42: 159400 | I42: 14.42038 | K42: 6036.1 | L42: 0.54606561 | N42: 275 | O42: 320
A43: 1993 | B43: JAN | C43: 128950 | D43: 9.1719301 | F43: 145372.13 | G43: 10.34 | H43: 193125 | I43: 13.736557 | K43: 7099 | L43: 0.50493627 | N43: 270 | O43: 314
B44: FEV | C44: 137100 | D44: 7.6735318 | F44: 177951.44 | G44: 9.96 | H44: 209875 | I44: 11.746772 | K44: 8078 | L44: 0.4521283 | N44: 262 | O44: 260
B45: MAR | C45: 164300 | D45: 7.2423521 | F45: 202812.84 | G45: 8.94 | H45: 270000 | I45: 11.901613 | K45: 9807 | L45: 0.43229304 | N45: 260 | O45: 247
B46: ABR | C46: 199900 | D46: 7.1668782 | F46: 247961.66 | G46: 8.89 | H46: 338750 | I46: 12.144972 | K46: 13141.25 | L46: 0.47114426 | N46: 260 | O46: 240
B47: MAI | C47: 271450 | D47: 7.4481279 | F47: 329466.42 | G47: 9.04 | H47: 446250 | I47: 12.244344 | K47: 16957.5 | L47: 0.46528506 | N47: 225 | O47: 230
B48: JUN | C48: 363000 | D48: 7.753925 | F48: 426484.65 | G48: 9.11 | H48: 574000 | I48: 12.261027 | K48: 22147.8 | L48: 0.47309196 | N48: 203 | O48: 228
B49: JUL | C49: 482500 | D49: 8.3189655 | F49: 521420 | G49: 8.99 | H49: 790000 | I49: 13.62069 | K49: 30962.5 | L49: 0.53383621 | N49: 215 | O49: 225
B50: AGO | C50: 768.5 | D50: 10.00651 | F50: 745.728 | G50: 9.71 | H50: 1157.5 | I50: 15.071615 | K50: 42.77 | L50: 0.55690104 | N50: 210 | O50: 250
B51: SET | C51: 1039 | D51: 8.8050847 | F51: 1045.48 | G51: 8.86 | H51: 1634 | I51: 13.847458 | K51: 56.9 | L51: 0.48220339 | N51: 215 | O51: 275
B52: OUT | C52: 1410 | D52: 9.7241379 | F52: 1492.05 | G52: 10.29 | H52: 2073.75 | I52: 14.301724 | K52: 74.89 | L52: 0.51648276 | N52: 270 | O52: 303
B53: NOV | C53: 1950.38 | D53: 9.3319617 | F53: 2039.84 | G53: 9.76 | H53: 2917.88 | I53: 13.961148 | K53: 98 | L53: 0.46889952 | N53: 340 | O53: 475
B54: DEZ | C54: 2977.5 | D54: 11.364504 | F54: 3298.58 | G54: 12.59 | H54: 4225 | I54: 16.125954 | K54: 168.4 | L54: 0.64274809 | N54: 330 | O54: 540
A55: 1994 | B55: JAN | C55: 4194.5 | D55: 10.994758 | F55: 4722.97 | G55: 12.38 | H55: 5983.75 | I55: 15.684797 | K55: 226.38 | L55: 0.5933945 | N55: 360 | O55: 525
B56: FEV | C56: 5135 | D56: 8.9548855 | F56: 5980.8749 | G56: 10.43 | H56: 7323.13 | I56: 12.770748 | K56: 301.38 | L56: 0.52557418 | N56: 394 | O56: 518
B57: MAR | C57: 6613.5 | D57: 8.6225554 | F57: 7117.76 | G57: 9.28 | H57: 9721 | I57: 12.674055 | K57: 386 | L57: 0.50325945 | N57: 277 | O57: 496
B58: ABR | C58: 9142 | D58: 8.4335793 | F58: 9170.64 | G58: 8.46 | H58: 13875 | I58: 12.799815 | K58: 571.25 | L58: 0.52698339 | N58: 300 | O58: 465
B59: MAI | C59: 14248 | D59: 9.1333333 | F59: 12214.8 | G59: 7.83 | H59: 19293.75 | I59: 12.367788 | K59: 794.65 | L59: 0.50939103 | N59: 250 | O59: 408
B60: JUN | C60: 17900.5 | D60: 8.95025 | F60: 18540 | G60: 9.27 | H60: 32808.9 | I60: 16.40445 | K60: 1417.5 | L60: 0.70875 | N60: 236 | O60: 401
B61: JUL | C61: 10 | D61: 10.752688 | F61: 9.0024 | G61: 9.68 | H61: 13.9 | I61: 14.946237 | K61: 0.67 | L61: 0.72043011 | N61: 220 | O61: 320
B62: AGO | C62: 10.8 | D62: 12.134831 | F62: 9.6031 | G62: 10.79 | H62: 14.5 | I62: 16.292135 | K62: 0.61 | L62: 0.68539326 | N62: 262 | O62: 310
B63: SET | C63: 11.8 | D63: 13.833529 | F63: 9.59625 | G63: 11.25 | H63: 14.5 | I63: 16.998828 | K63: 0.57 | L63: 0.66822978 | N63: 250 | O63: 320
B64: OUT | C64: 12.2 | D64: 14.52381 | F64: 10.8024 | G64: 12.86 | H64: 14.9 | I64: 17.738095 | K64: 0.58 | L64: 0.69047619 | N64: 268 | O64: 300
B65: NOV | C65: 12 | D65: 14.285714 | F65: 10.8024 | G65: 12.86 | H65: 15.1 | I65: 17.97619 | K65: 0.59 | L65: 0.70238095 | N65: 275 | O65: 295
B66: DEZ | C66: 12 | D66: 14.117647 | F66: 11.3985 | G66: 13.41 | H66: 14.94 | I66: 17.576471 | K66: 0.59 | L66: 0.69411765 | N66: 272 | O66: 316
A67: 1995 | B67: JAN | C67: 11.8 | D67: 14.014252 | E67: 129.29832 | F67: 11.3985 | G67: 13.537411 | H67: 14.63 | I67: 17.375297 | J67: 160.308 | K67: 0.53 | L67: 0.62945368 | M67: 5.807467 | N67: 295 | O67: 310
B68: FEV | C68: 9.5 | D68: 11.156782 | E68: 102.90983 | F68: 10.8024 | G68: 12.686318 | H68: 13.91 | I68: 16.335878 | J68: 150.68166 | K68: 0.55 | L68: 0.64591897 | M68: 5.9579376 | N68: 295 | O68: 309
B69: MAR | C69: 8.5 | D69: 9.4866071 | E69: 90.436783 | F69: 10.1992 | G69: 11.383036 | H69: 13.5 | I69: 15.066964 | J69: 143.63489 | K69: 0.55 | L69: 0.61383929 | M69: 5.8517919 | N69: 295 | O69: 310
B70: ABR | C70: 7.7 | D70: 8.4337349 | E70: 80.081639 | F70: 8.9979 | G70: 9.8553122 | H70: 13.05 | I70: 14.293538 | J70: 135.72278 | K70: 0.53 | L70: 0.58050383 | M70: 5.5121128 | N70: 300 | O70: 314
B71: MAI | C71: 8.6 | D71: 9.4922737 | E71: 89.086616 | F71: 8.397 | G71: 9.2682119 | H71: 12.85 | I71: 14.183223 | J71: 133.11198 | K71: 0.51 | L71: 0.56291391 | M71: 5.2830435 | N71: 330 | O71: 348
B72: JUN | C72: 9.4 | D72: 10.195228 | E72: 94.884359 | F72: 8.3993 | G72: 9.1098698 | H72: 13.35 | I72: 14.479393 | J72: 134.75598 | K72: 0.53 | L72: 0.57483731 | M72: 5.3498628 | N72: 345 | O72: 390
B73: JUL | C73: 9.8 | D73: 10.470085 | E73: 96.756463 | F73: 8.3996 | G73: 8.9739316 | H73: 14.4 | I73: 15.384615 | J73: 142.17276 | K73: 0.55 | L73: 0.58760684 | M73: 5.4302096 | N73: 368 | O73: 380
B74: AGO | C74: 11.5 | D74: 12.092534 | E74: 112.09606 | F74: 8.4036 | G74: 8.8365931 | H74: 15.27 | I74: 16.056782 | J74: 148.84407 | K74: 0.59 | L74: 0.62039958 | M74: 5.7510152 | N74: 375 | O74: 364
B75: SET | C75: 10.8 | D75: 11.320755 | E75: 106.42331 | F75: 8.9965 | G75: 9.4302935 | H75: 15.53 | I75: 16.278826 | J75: 153.03277 | K75: 0.62 | L75: 0.64989518 | M75: 6.1094861 | N75: 385 | O75: 379
B76: OUT | C76: 10.8 | D76: 11.227778 | E76: 106.18279 | F76: 9.0048 | G76: 9.3614721 | H76: 15.5 | I76: 16.113941 | J76: 152.39197 | K76: 0.62 | L76: 0.64455765 | M76: 6.0956789 | N76: 395 | O76: 440
B77: NOV | C77: 11.58 | D77: 11.980137 | E77: 112.36041 | F77: 9.0048 | G77: 9.3159528 | H77: 15.53 | I77: 16.066625 | J77: 150.68714 | K77: 0.64 | L77: 0.66211463 | M77: 6.2099015 | N77: 400 | O77: 405
B78: DEZ | C78: 12.28 | D78: 12.627249 | E78: 118.82652 | F78: 10.2044 | G78: 10.492956 | H78: 16.35 | I78: 16.812339 | J78: 158.20958 | K78: 0.63 | L78: 0.64781491 | M78: 6.0961489 | N78: 370 | O78: 397
A79: 1996 | B79: JAN | C79: 12.5 | D79: 12.827091 | E79: 118.82362 | F79: 10.2044 | G79: 10.471421 | H79: 16 | I79: 16.418676 | J79: 152.09423 | K79: 0.69 | L79: 0.70805541 | M79: 6.5590636 | N79: 365 | O79: 385
B80: FEV | C80: 11 | D80: 11.211905 | E80: 103.77363 | F80: 10.2018 | G80: 10.398328 | H80: 15.5 | I80: 15.798593 | J80: 146.22648 | K80: 0.7 | L80: 0.71348486 | M80: 6.6037767 | N80: 365 | O80: 383
B81: MAR | C81: 10 | D81: 10.140959 | E81: 94.135532 | F81: 10.7996 | G81: 10.95183 | H81: 14.25 | I81: 14.450867 | J81: 134.14313 | K81: 0.65 | L81: 0.65916236 | M81: 6.1188096 | N81: 380 | O81: 397
B82: ABR | C82: 10.5 | D82: 10.603918 | E82: 98.158601 | F82: 10.197 | G82: 10.29792 | H82: 14.3 | I82: 14.441527 | J82: 133.68267 | K82: 0.7 | L82: 0.70692789 | M82: 6.5439067 | N82: 365 | O82: 400
B83: MAI | C83: 11 | D83: 11.051944 | E83: 101.13077 | F83: 10.8009 | G83: 10.851904 | H83: 14.3 | I83: 14.367527 | J83: 131.47 | K83: 0.61 | L83: 0.61288054 | M83: 5.6081609 | N83: 345 | O83: 408
B84: JUN | C84: 10.7 | D84: 10.686108 | E84: 97.184601 | F84: 10.8009 | G84: 10.786877 | H84: 14 | I84: 13.981824 | J84: 127.15742 | K84: 0.63 | L84: 0.62918206 | M84: 5.722084 | N84: 374 | O84: 416
B85: JUL | C85: 10.7 | D85: 10.626676 | E85: 96.134186 | F85: 10.8 | G85: 10.725991 | H85: 14 | I85: 13.904062 | J85: 125.78305 | K85: 0.63 | L85: 0.62568279 | M85: 5.6602371 | N85: 375 | O85: 441
B86: AGO | C86: 10.8 | D86: 10.657194 | E86: 97.02898 | F86: 10.8 | G86: 10.657194 | H86: 14.5 | I86: 14.308269 | J86: 130.27039 | K86: 0.57 | L86: 0.562463 | M86: 5.1209739 | N86: 365 | O86: 446
B87: SET | C87: 12 | D87: 11.772785 | E87: 107.67202 | F87: 10.8 | G87: 10.595507 | H87: 16.5 | I87: 16.18758 | J87: 148.04903 | K87: 0.67 | L87: 0.65731384 | M87: 6.0116877 | N87: 338 | O87: 420
B88: OUT | C88: 12.25 | D88: 11.950054 | E88: 109.67412 | F88: 11.4029 | G88: 11.123695 | H88: 16.5 | I88: 16.095991 | J88: 147.72433 | K88: 0.64 | L88: 0.62432933 | M88: 5.7299134 | N88: 322 | O88: 410
B89: NOV | C89: 13 | D89: 12.61646 | E89: 116.0611 | F89: 11.4036 | G89: 11.067158 | H89: 16.8 | I89: 16.304348 | J89: 149.98665 | K89: 0.63 | L89: 0.61141304 | M89: 5.6244995 | N89: 327 | O89: 413
B90: DEZ | C90: 13.8 | D90: 13.303769 | E90: 122.13127 | F90: 11.4021 | G90: 10.992095 | H90: 17.5 | I90: 16.870722 | J90: 154.8766 | K90: 0.65 | L90: 0.62662682 | M90: 5.7525596 | N90: 337 | O90: 416
A91: 1997 | B91: JAN | C91: 13.3 | D91: 12.752901 | E91: 115.878 | F91: 12.035066 | G91: 11.54 | H91: 21.81 | I91: 20.912839 | J91: 190.0225 | K91: 0.72 | L91: 0.69038259 | M91: 6.2730949 | N91: 367 | O91: 424
B92: FEV | C92: 12.5 | D92: 11.912704 | E92: 108.45131 | F92: 12.108922 | G92: 11.54 | H92: 22 | I92: 20.966359 | J92: 190.8743 | K92: 0.73 | L92: 0.6957019 | M92: 6.3335563 | N92: 359 | O92: 438
B93: MAR | C93: 11.2 | D93: 10.599035 | E93: 96.053759 | F93: 11.961844 | G93: 11.32 | H93: 22.26 | I93: 21.065582 | J93: 190.90685 | K93: 0.73 | L93: 0.69082994 | M93: 6.2606468 | N93: 341 | O93: 435
B94: ABR | C94: 11.4 | D94: 10.745593 | E94: 97.197665 | F94: 13.208205 | G94: 12.45 | H94: 22.5 | I94: 21.208408 | J94: 191.8375 | K94: 0.72 | L94: 0.67866905 | M94: 6.1387999 | N94: 319 | O94: 435
B95: MAI | C95: 11.5 | D95: 10.764766 | E95: 97.755208 | F95: 11.975643 | G95: 11.21 | H95: 22.5 | I95: 21.0615 | J95: 191.26019 | K95: 0.71 | L95: 0.66460732 | M95: 6.0353215 | N95: 335 | O95: 435
B96: JUN | C96: 11.65 | D96: 10.841243 | E96: 98.344392 | F96: 12.658788 | G96: 11.78 | H96: 22.5 | I96: 20.938023 | J96: 189.93552 | K96: 0.72 | L96: 0.67001675 | M96: 6.0779366 | N96: 335 | O96: 442
B97: JUL | C97: 11.8 | D97: 10.918849 | E97: 99.523937 | F97: 12.611769 | G97: 11.67 | H97: 22.5 | I97: 20.819839 | J97: 189.77022 | K97: 0.72 | L97: 0.66623485 | M97: 6.072647 | N97: 339 | O97: 423
B98: AGO | C98: 12.57 | D98: 11.554371 | E98: 106.06483 | F98: 13.173258 | G98: 12.108887 | H98: 22.5 | I98: 20.682048 | J98: 189.85351 | K98: 0.72 | L98: 0.66182554 | M98: 6.0753122 | N98: 297 | O98: 408
B99: SET | C99: 14.76 | D99: 13.496708 | E99: 123.81382 | F99: 13.17788 | G99: 12.05 | H99: 23.1 | I99: 21.122897 | J99: 193.77366 | K99: 0.75 | L99: 0.68580834 | M99: 6.2913526 | N99: 285 | O99: 412
B100: OUT | C100: 15.46 | D100: 14.053268 | E100: 129.24372 | F100: 12.607146 | G100: 11.46 | H100: 24 | I100: 21.816199 | J100: 200.63708 | K100: 0.81 | L100: 0.7362967 | M100: 6.7715016 | N100: 279 | O100: 423
B101: NOV | C101: 15.5 | D101: 13.998013 | E101: 128.511 | F101: 12.678585 | G101: 11.45 | H101: 24 | I101: 21.674343 | J101: 198.98477 | K101: 0.84 | L101: 0.758602 | M101: 6.9644671 | N101: 269 | O101: 424
B102: DEZ | C102: 15.13 | D102: 13.586566 | E102: 124.58199 | F102: 13.842048 | G102: 12.43 | H102: 24 | I102: 21.551724 | J102: 197.61849 | K102: 0.86 | L102: 0.77227011 | M102: 7.0813291 | N102: 285 | O102: 425
A103: 1998 | B103: JAN | C103: 14.62 | D103: 13.054737 | E103: 119.33323 | F103: 13.797168 | G103: 12.32 | H103: 24 | I103: 21.430485 | J103: 195.89586 | K103: 0.87 | L103: 0.77685508 | M103: 7.101225 | N103: 299 | O103: 420
...

Sheet Arroz Charts

Sheet Milho
C4: MILHO | D4: MILHO | E4: MILHO | F4: MILHO | G4: MILHO | H4: MILHO | I4: MILHO | J4: MILHO | K4: MILHO | L4: MILHO | M4: MILHO | N4: MILHO | O4: MILHO | P4: MILHO | Q4: MILHO | R4: MILHO | S4: MILHO | T4: MILHO | U4: MILHO | V4: MILHO | W4: MILHO | X4: MILHO | Y4: DDG | Z4: DDG | AA4: DDG | AB4: SORGO | AC4: SORGO | AD4: SORGO
A5: Ano | B5: Mês | C5: GO | D5: GO | E5: GO | F5: MS | G5: MS | H5: MS | I5: MT | J5: MT | K5: MT | L5: PR | M5: PR | N5: PR | O5: RS | P5: RS | Q5: RS | R5: SP | S5: SP | T5: SP | U5: CBOT | V5: EUA FOB Golfo | W5: Argentina FOB | X5: Paranaguá | Y5: MT | Z5: MT | AA5: MT | AB5: GO | AC5: GO | AD5: GO
C6: R$/60 kg | D6: US$/60 kg | E6: Deflacionado | F6: R$/60 kg | G6: US$/60 kg | H6: Deflacionado | I6: R$/60 kg | J6: US$/60 kg | K6: Deflacionado | L6: R$/60 kg | M6: US$/60 kg | N6: Deflacionado | O6: R$/60 kg | P6: US$/60 kg | Q6: Deflacionado | R6: R$/60 kg | S6: US$/60 kg | T6: Deflacionado | U6: US$/bushel | V6: US$/t | W6: US$/t | X6: US$/t | Y6: R$/t | Z6: US$/t | AA6: Deflacionado | AB6: R$/60 kg | AC6: US$/60 kg | AD6: Deflacionado
A7: 1990 | B7: JAN | C7: 94.5 | D7: 6.6019282 | L7: 108.5 | M7: 7.5799916 | O7: 69.6 | P7: 4.8623725 | R7: 108.5 | S7: 7.5799916 | U7: 2.3981 | V7: 94.409669 | W7: 104 | X7: 126.33
B8: FEV | C8: 135 | D8: 5.7055915 | L8: 156.25 | M8: 6.6036938 | O8: 129 | P8: 5.4520096 | R8: 172.5 | S8: 7.290478 | U8: 2.4135 | V8: 95.015944 | W8: 104 | X8: 121.51
B9: MAR | C9: 231.67 | D9: 6.137604 | L9: 243.33 | M9: 6.4465109 | O9: 208.8 | P9: 5.531712 | R9: 286.67 | S9: 7.594712 | U9: 2.5517 | V9: 100.45667 | W9: 105 | X9: 126.58
B10: ABR | C10: 238.75 | D10: 4.9930985 | L10: 281.25 | M10: 5.8819224 | O10: 261.6 | P10: 5.4709721 | R10: 277.5 | S10: 5.8034967 | U10: 2.735 | V10: 107.67293 | W10: 111 | X10: 96.72
B11: MAI | C11: 322 | D11: 6.1682279 | L11: 377.5 | M11: 7.2313852 | O11: 337.2 | P11: 6.4593989 | R11: 392 | S11: 7.509147 | U11: 2.846 | V11: 112.04283 | W11: 113 | X11: 125.15
B12: JUN | C12: 350 | D12: 6.1219849 | L12: 435 | M12: 7.6087527 | O12: 426.6 | P12: 7.4618251 | R12: 430 | S12: 7.5212958 | U12: 2.8542 | V12: 112.36565 | W12: 117 | X12: 125.35
B13: JUL | C13: 403.75 | D13: 6.0611292 | L13: 478.75 | M13: 7.1870356 | O13: 459.6 | P13: 6.8995541 | R13: 537.5 | S13: 8.0689955 | U13: 2.6867 | V13: 105.77143 | W13: 126 | X13: 134.48
B14: AGO | C14: 526 | D14: 7.3318279 | L14: 630 | M14: 8.7814669 | O14: 556.8 | P14: 7.7611441 | R14: 675 | S14: 9.4087146 | U14: 2.5111 | V14: 98.858313 | W14: 127 | X14: 156.81
B15: SET | C15: 582.5 | D15: 7.6843924 | L15: 668.75 | M15: 8.8222102 | O15: 637.8 | P15: 8.413915 | R15: 748.75 | S15: 9.8775774 | U15: 2.2946 | V15: 90.335026 | W15: 127 | X15: 164.63
B16: OUT | C16: 633 | D16: 6.6322308 | L16: 774 | M16: 8.1095523 | O16: 687 | P16: 7.1980135 | R16: 806 | S16: 8.4448309 | U16: 2.2979 | V16: 90.464942 | W16: 128 | X16: 140.75
B17: NOV | C17: 823.75 | D17: 6.7586971 | L17: 981.25 | M17: 8.0509518 | O17: 816.6 | P17: 6.7000328 | R17: 1019.75 | S17: 8.3668362 | U17: 2.2598 | V17: 88.965001 | W17: 128 | X17: 139.45
B18: DEZ | C18: 868.75 | D18: 5.5862419 | L18: 1075 | M18: 6.912472 | O18: 1115.4 | P18: 7.1722524 | R18: 1200 | S18: 7.7162478 | U18: 2.3647 | V18: 93.09476 | W18: 128 | X18: 128.6
A19: 1991 | B19: JAN | C19: 1045 | D19: 4.7469792 | L19: 1180 | M19: 5.3602253 | O19: 1150.8 | P19: 5.2275824 | R19: 1290 | S19: 5.8599073 | U19: 2.3752 | V19: 93.50813 | W19: 97 | X19: 97.67
B20: FEV | C20: 1197.5 | D20: 5.3596205 | L20: 1281.25 | M20: 5.7344582 | O20: 1311 | P20: 5.8676095 | R20: 1406.25 | S20: 6.2939176 | U20: 2.4031 | V20: 94.606512 | W20: 98 | X20: 104.9
B21: MAR | C21: 1156.25 | D21: 4.8392835 | L21: 1427.5 | M21: 5.9745532 | O21: 1369.2 | P21: 5.7305487 | R21: 1393.75 | S21: 5.8332985 | U21: 2.5403 | V21: 100.00787 | W21: 99 | X21: 97.22
B22: ABR | C22: 1450 | D22: 5.5613086 | L22: 1777.5 | M22: 6.8173973 | O22: 1565.4 | P22: 6.0039121 | R22: 1587.5 | S22: 6.0886741 | U22: 2.5555 | V22: 100.60628 | W22: 103 | X22: 101.48
B23: MAI | C23: 1645 | D23: 5.7780119 | L23: 1995 | M23: 7.0073762 | O23: 1879.8 | P23: 6.6027397 | R23: 1865 | S23: 6.5507552 | U23: 2.4909 | V23: 98.063068 | W23: 103 | X23: 109.18
B24: JUN | C24: 1568.75 | D24: 5.024341 | L24: 1987.5 | M24: 6.3654998 | O24: 1896.6 | P24: 6.0743683 | R24: 1893.75 | S24: 6.0652404 | U24: 2.3949 | V24: 94.28369 | W24: 105 | X24: 101.09
B25: JUL | C25: 1805 | D25: 5.2081831 | L25: 2280 | M25: 6.5787575 | O25: 2026.8 | P25: 5.8481692 | R25: 2220 | S25: 6.4056323 | U25: 2.354 | V25: 92.673517 | W25: 105 | X25: 106.76
B26: AGO | C26: 2258.75 | D26: 6.0233333 | L26: 2718.75 | M26: 7.25 | O26: 2248.8 | P26: 5.9968 | R26: 2831.25 | S26: 7.55 | U26: 2.4944 | V26: 98.200858 | W26: 106 | X26: 125.83
B27: SET | C27: 2568.75 | D27: 5.8380682 | L27: 3118.75 | M27: 7.0880682 | O27: 2709 | P27: 6.1568182 | R27: 3125 | S27: 7.1022727 | U27: 2.5151 | V27: 99.015787 | W27: 108 | X27: 118.37
B28: OUT | C28: 3890 | D28: 6.4833333 | L28: 4630 | M28: 7.7166667 | O28: 3567.6 | P28: 5.946 | R28: 4560 | S28: 7.6 | U28: 2.5086 | V28: 98.759891 | W28: 116 | X28: 126.67
B29: NOV | C29: 4887.5 | D29: 6.4735099 | L29: 5237.5 | M29: 6.9370861 | O29: 4961.4 | P29: 6.5713907 | R29: 5693.75 | S29: 7.5413907 | U29: 2.4343 | V29: 95.83481 | W29: 124 | X29: 125.69
B30: DEZ | C30: 5762.5 | D30: 5.8921268 | L30: 6212.5 | M30: 6.3522495 | O30: 5493.6 | P30: 5.6171779 | R30: 6837.5 | S30: 6.9913088 | U30: 2.5113 | V30: 98.866186 | W30: 122 | X30: 116.52
A31: 1992 | B31: JAN | C31: 8554 | D31: 7.1461988 | L31: 8230 | M31: 6.8755221 | O31: 5635.8 | P31: 4.7082707 | R31: 9840 | S31: 8.2205514 | U31: 2.5852 | V31: 101.77552 | W31: 114 | X31: 137.01
B32: FEV | C32: 8675 | D32: 5.885346 | L32: 8812.5 | M32: 5.9786296 | O32: 7901.4 | P32: 5.3605156 | R32: 10193 | S32: 6.9151967 | U32: 2.6457 | V32: 104.15732 | W32: 105 | X32: 115.25
B33: MAR | C33: 9050 | D33: 4.9917264 | L33: 9137.5 | M33: 5.039989 | O33: 8817 | P33: 4.8632101 | R33: 10775 | S33: 5.9431881 | U33: 2.7179 | V33: 106.99972 | W33: 106 | X33: 99.05
B34: ABR | C34: 10437.5 | D34: 4.7079387 | L34: 10537.5 | M34: 4.7530447 | O34: 9523.8 | P34: 4.2958051 | R34: 12562.5 | S34: 5.6664411 | U34: 2.2912 | V34: 90.201173 | W34: 96 | X34: 94.44
B35: MAI | C35: 12462.5 | D35: 4.7932692 | L35: 13400 | M35: 5.1538462 | O35: 11389.8 | P35: 4.3806923 | R35: 14675 | S35: 5.6442308 | U35: 2.5863 | V35: 101.81883 | W35: 100 | X35: 94.07
B36: JUN | C36: 14812.5 | D36: 4.3566176 | L36: 17000 | M36: 5 | O36: 15274.8 | P36: 4.4925882 | R36: 17062.5 | S36: 5.0183824 | U36: 2.5565 | V36: 100.64564 | W36: 108 | X36: 83.64
B37: JUL | C37: 19650 | D37: 5.1038961 | L37: 21320 | M37: 5.5376623 | O37: 18627 | P37: 4.8381818 | R37: 22000 | S37: 5.7142857 | U37: 2.3288 | V37: 91.68143 | W37: 105 | X37: 95.24
B38: AGO | C38: 27937.5 | D38: 6.0080645 | L38: 27875 | M38: 5.9946237 | O38: 23460 | P38: 5.0451613 | R38: 32625 | S38: 7.016129 | U38: 2.193 | V38: 86.335184 | W38: 102 | X38: 116.94
B39: SET | C39: 37700 | D39: 6.5474123 | L39: 39400 | M39: 6.8426537 | O39: 31980 | P39: 5.5540118 | R39: 44300 | S39: 7.6936436 | U39: 2.1839 | V39: 85.97693 | W39: 102 | X39: 128.23
B40: OUT | C40: 48250 | D40: 6.5645365 | L40: 51000 | M40: 6.9386811 | O40: 43080 | P40: 5.8611447 | R40: 56875 | S40: 7.73799 | U40: 2.0889 | V40: 82.23692 | W40: 103 | X40: 128.97
B41: NOV | C41: 63250 | D41: 7.1289294 | L41: 64875 | M41: 7.3120837 | O41: 53340 | P41: 6.0119698 | R41: 74125 | S41: 8.3546544 | U41: 2.1195 | V41: 83.441597 | W41: 114 | X41: 139.24
B42: DEZ | C42: 81700 | D42: 7.3911234 | L42: 82100 | M42: 7.4273101 | O42: 72840 | P42: 6.5895891 | R42: 100900 | S42: 9.1280827 | U42: 2.1999 | V42: 86.606827 | W42: 118 | X42: 152.13
A43: 1993 | B43: JAN | C43: 96250 | D43: 6.846051 | L43: 101125 | M43: 7.192799 | O43: 83880 | P43: 5.9662001 | R43: 115500 | S43: 8.2152612 | U43: 2.1771 | V43: 85.709224 | W43: 118 | X43: 136.92
B44: FEV | C44: 96875 | D44: 5.4221254 | L44: 106625 | M44: 5.9678361 | O44: 104460 | P44: 5.8466603 | R44: 119375 | S44: 6.6814578 | U44: 2.1244 | V44: 83.634503 | W44: 96 | X44: 111.36
B45: MAR | C45: 120400 | D45: 5.3072379 | L45: 124300 | M45: 5.4791501 | O45: 114480 | P45: 5.0462841 | R45: 143700 | S45: 6.3343031 | U45: 2.242 | V45: 88.264242 | W45: 84 | X45: 105.57
B46: ABR | C46: 162375 | D46: 5.82152 | L46: 171125 | M46: 6.1352278 | O46: 144720 | P46: 5.1885473 | R46: 198250 | S46: 7.1077219 | U46: 2.2866 | V46: 90.020078 | W46: 90 | X46: 118.46
B47: MAI | C47: 205625 | D47: 5.6420015 | L47: 223750 | M47: 6.1393207 | O47: 193740 | P47: 5.3158972 | R47: 252500 | S47: 6.928172 | U47: 2.2857 | V47: 89.984646 | W47: 95 | X47: 115.47
B48: JUN | C48: 277500 | D48: 5.9275873 | L48: 300000 | M48: 6.4082025 | O48: 262200 | P48: 5.600769 | R48: 325000 | S48: 6.9422194 | U48: 2.1819 | V48: 85.898193 | W48: 97 | X48: 115.7
B49: JUL | C49: 396250 | D49: 6.8318966 | L49: 420625 | M49: 7.2521552 | O49: 348000 | P49: 6 | R49: 479375 | S49: 8.2650862 | U49: 2.4083 | V49: 94.811228 | W49: 106 | X49: 137.75
B50: AGO | C50: 570 | D50: 7.421875 | L50: 597.5 | M50: 7.7799479 | O50: 526.8 | P50: 6.859375 | R50: 668.75 | S50: 8.7076823 | U50: 2.3736 | V50: 93.44514 | W50: 122 | X50: 145.13
B51: SET | C51: 729.5 | D51: 6.1822034 | L51: 785.5 | M51: 6.6567797 | O51: 710.4 | P51: 6.020339 | R51: 877 | S51: 7.4322034 | U51: 2.4069 | V51: 94.756112 | W51: 124 | X51: 123.87
B52: OUT | C52: 1065.63 | D52: 7.3491724 | L52: 1113.13 | M52: 7.6767586 | O52: 929.4 | P52: 6.4096552 | R52: 1228.75 | S52: 8.4741379 | U52: 2.4885 | V52: 97.968584 | W52: 129 | X52: 141.24
B53: NOV | C53: 1467.5 | D53: 7.0215311 | L53: 1549.38 | M53: 7.4133014 | O53: 1320.07 | P53: 6.3161244 | R53: 1666.25 | S53: 7.972488 | U53: 2.7371 | V53: 107.7556 | W53: 134 | X53: 132.87
B54: DEZ | C54: 2041.5 | D54: 7.7919847 | L54: 2086.5 | M54: 7.9637405 | O54: 1905.6 | P54: 7.2732824 | R54: 2270 | S54: 8.6641221 | U54: 2.9638 | V54: 116.68045 | W54: 134 | X54: 144.4
A55: 1994 | B55: JAN | C55: 2387.5 | D55: 6.2581913 | L55: 2568.75 | M55: 6.7332896 | O55: 2528.4 | P55: 6.6275229 | R55: 2808.13 | S55: 7.3607602 | U55: 3.0205 | V55: 118.91264 | W55: 129 | X55: 122.68
B56: FEV | C56: 2838.75 | D56: 4.9504735 | L56: 3045.63 | M56: 5.3112498 | O56: 3115.8 | P56: 5.4336188 | R56: 3315 | S56: 5.781002 | U56: 2.9066 | V56: 114.42857 | W56: 118 | X56: 96.35
B57: MAR | C57: 4235 | D57: 5.5215124 | L57: 4280 | M57: 5.5801825 | O57: 3958.8 | P57: 5.1614081 | R57: 5028 | S57: 6.5554107 | U57: 2.8455 | V57: 112.02315 | W57: 108 | X57: 109.26
B58: ABR | C58: 6075 | D58: 5.6042435 | L58: 6375 | M58: 5.8809963 | O58: 5598.6 | P58: 5.1647601 | R58: 7132.2 | S58: 6.5795203 | U58: 2.6707 | V58: 105.14153 | W58: 105 | X58: 109.66
B59: MAI | C59: 8050 | D59: 5.1602564 | L59: 9100 | M59: 5.8333333 | O59: 8236.8 | P59: 5.28 | R59: 9881.25 | S59: 6.3341346 | U59: 2.6561 | V59: 104.56675 | W59: 108 | X59: 105.57
B60: JUN | C60: 12230 | D60: 6.115 | L60: 13468 | M60: 6.734 | O60: 11786.4 | P60: 5.8932 | R60: 14740 | S60: 7.37 | U60: 2.7146 | V60: 106.86981 | W60: 110 | X60: 122.83
B61: JUL | C61: 6.03 | D61: 6.483871 | L61: 6.38 | M61: 6.8602151 | O61: 5.4 | P61: 5.8064516 | R61: 7.03 | S61: 7.5591398 | U61: 2.2398 | V61: 88.177631 | W61: 103 | X61: 125.99
B62: AGO | C62: 5.85 | D62: 6.5730337 | L62: 6.21 | M62: 6.9775281 | O62: 5.4 | P62: 6.0674157 | R62: 6.82 | S62: 7.6629213 | U62: 2.1926 | V62: 86.319436 | W62: 100 | X62: 127.72
B63: SET | C63: 6.08 | D63: 7.1277843 | L63: 6.31 | M63: 7.3974209 | O63: 5.4 | P63: 6.3305979 | R63: 7.33 | S63: 8.5932005 | U63: 2.2014 | V63: 86.665879 | W63: 109 | X63: 143.22
B64: OUT | C64: 6.5 | D64: 7.7380952 | L64: 7.03 | M64: 8.3690476 | O64: 6 | P64: 7.1428571 | R64: 7.88 | S64: 9.3809524 | U64: 2.16 | V64: 85.036022 | W64: 116 | X64: 156.35
B65: NOV | C65: 6.69 | D65: 7.9642857 | L65: 7.09 | M65: 8.4404762 | O65: 6 | P65: 7.1428571 | R65: 8.14 | S65: 9.6904762 | U65: 2.1575 | V65: 84.937601 | W65: 123 | X65: 161.51
B66: DEZ | C66: 6.33 | D66: 7.4470588 | L66: 6.78 | M66: 7.9764706 | O66: 6 | P66: 7.0588235 | R66: 7.45 | S66: 8.7647059 | U66: 2.2927 | V66: 90.260226 | W66: 128 | X66: 146.08
A67: 1995 | B67: JAN | C67: 5.95 | D67: 7.0665083 | E67: 65.197035 | L67: 6.51 | M67: 7.7315914 | N67: 71.333227 | O67: 6 | P67: 7.1258907 | Q67: 65.74491 | R67: 7.09 | S67: 8.4204276 | T67: 77.688568 | U67: 2.3254 | V67: 91.547577 | W67: 126 | X67: 139.02
B68: FEV | C68: 5.55 | D68: 6.5179096 | E68: 60.121007 | L68: 5.33 | M68: 6.259542 | N68: 57.737832 | O68: 5.4 | P68: 6.3417499 | Q68: 58.496115 | R68: 6.75 | S68: 7.9271873 | T68: 73.120144 | U68: 2.335 | V68: 91.925515 | W68: 97 | X68: 133.93
B69: MAR | C69: 4.68 | D69: 5.2232143 | E69: 49.793429 | L69: 5.05 | M69: 5.6361607 | N69: 53.730089 | O69: 4.8 | P69: 5.3571429 | Q69: 51.070183 | R69: 6.13 | S69: 6.8415179 | T69: 65.22088 | U69: 2.4632 | V69: 96.97256 | W69: 96 | X69: 116.1
B70: ABR | C70: 4.83 | D70: 5.2902519 | E70: 50.233028 | L70: 5.67 | M70: 6.2102957 | N70: 58.969207 | O70: 4.8 | P70: 5.2573932 | Q70: 49.921022 | R70: 6.14 | S70: 6.7250821 | T70: 63.857307 | U70: 2.6072 | V70: 102.64163 | W70: 101 | X70: 114.98
B71: MAI | C71: 4.69 | D71: 5.1766004 | E71: 48.583282 | L71: 5.69 | M71: 6.2803532 | N71: 58.942191 | O71: 4.8 | P71: 5.2980132 | Q71: 49.722762 | R71: 5.98 | S71: 6.6004415 | T71: 61.946275 | U71: 2.6076 | V71: 102.65738 | W71: 109 | X71: 110.74
B72: JUN | C72: 4.8 | D72: 5.2060738 | E72: 48.451588 | L72: 5.8 | M72: 6.2906725 | N72: 58.545669 | O72: 5.4 | P72: 5.856833 | Q72: 54.508036 | R72: 5.97 | S72: 6.4750542 | T72: 60.261662 | U72: 2.6072 | V72: 102.64163 | W72: 130 | X72: 109.34
B73: JUL | C73: 5.48 | D73: 5.8547009 | E73: 54.104634 | L73: 6.57 | M73: 7.0192308 | N73: 64.866322 | O73: 5.4 | P73: 5.7692308 | Q73: 53.314786 | R73: 6.48 | S73: 6.9230769 | T73: 63.977743 | U73: 2.857 | V73: 112.47589 | W73: 136 | X73: 117.39
B74: AGO | C74: 5.3 | D74: 5.573081 | E74: 51.661662 | L74: 6.09 | M74: 6.4037855 | N74: 59.362174 | O74: 5.4 | P74: 5.6782334 | Q74: 52.63641 | R74: 6.17 | S74: 6.4879075 | T74: 60.141973 | U74: 2.829 | V74: 111.37357 | W74: 134 | X74: 109.4
B75: SET | C75: 5.41 | D75: 5.6708595 | E75: 53.310193 | L75: 5.93 | M75: 6.2159329 | N75: 58.434278 | O75: 5.4 | P75: 5.6603774 | Q75: 53.211653 | R75: 6.26 | S75: 6.5618449 | T75: 61.686101 | U75: 3.0345 | V75: 119.4638 | W75: 141 | X75: 109.82
B76: OUT | C76: 6 | D76: 6.2376546 | E76: 58.990441 | L76: 6.5 | M76: 6.7574592 | N76: 63.906311 | O76: 6 | P76: 6.2376546 | Q76: 58.990441 | R76: 6.75 | S76: 7.0173615 | T76: 66.364246 | U76: 3.2286 | V76: 127.10523 | W76: 147 | X76: 117.19
B77: NOV | C77: 6.06 | D77: 6.2693979 | E77: 58.800005 | L77: 6.56 | M77: 6.7866749 | N77: 63.65149 | O77: 6.6 | P77: 6.8280571 | Q77: 64.039609 | R77: 7.08 | S77: 7.3246431 | T77: 68.697035 | U77: 3.28 | V77: 129.12877 | W77: 148 | X77: 122.92
B78: DEZ | C78: 5.95 | D78: 6.1182519 | E78: 57.57474 | L78: 6.45 | M78: 6.6323907 | N78: 62.412953 | O78: 6.6 | P78: 6.7866324 | Q78: 63.864418 | R78: 6.78 | S78: 6.9717224 | T78: 65.606174 | U78: 3.5038 | V78: 137.93945 | W78: 148 | X78: 116.49
A79: 1996 | B79: JAN | C79: 6.06 | D79: 6.2185736 | E79: 57.605689 | L79: 6.84 | M79: 7.0189841 | N79: 65.020283 | O79: 6.6 | P79: 6.772704 | Q79: 62.738869 | R79: 8.34 | S79: 8.558235 | T79: 79.279117 | U79: 3.6227 | V79: 142.62037 | W79: 151 | X79: 143.3
B80: FEV | C80: 5.8 | D80: 5.9117317 | E80: 54.717007 | L80: 6.29 | M80: 6.4111711 | N80: 59.339651 | O80: 6.6 | P80: 6.727143 | Q80: 62.264181 | R80: 7.1 | S80: 7.236775 | T80: 66.981164 | U80: 3.7435 | V80: 147.37609 | W80: 159 | X80: 120.75
B81: MAR | C81: 5.7 | D81: 5.7803468 | E81: 53.657253 | L81: 6.6 | M81: 6.6930332 | N81: 62.129451 | O81: 6.6 | P81: 6.6930332 | Q81: 62.129451 | R81: 6.8 | S81: 6.8958523 | T81: 64.012162 | U81: 3.895 | V81: 153.34042 | W81: 163 | X81: 115.65
B82: ABR | C82: 6.22 | D82: 6.2815593 | E82: 58.147285 | L82: 7.45 | M82: 7.5237326 | N82: 69.645864 | O82: 7.2 | P82: 7.2712583 | Q82: 67.308755 | R82: 7.12 | S82: 7.1904666 | T82: 66.56088 | U82: 4.5417 | V82: 178.80005 | W82: 185 | X82: 119.87
B83: MAI | C83: 6.63 | D83: 6.6613081 | E83: 60.954273 | L83: 8.39 | M83: 8.4296192 | N83: 77.135196 | O83: 7.8 | P83: 7.8368331 | Q83: 71.71091 | R83: 7.94 | S83: 7.9774942 | T83: 72.998029 | U83: 4.8133 | V83: 189.49254 | W83: 199 | X83: 133.67
B84: JUN | C84: 6.3 | D84: 6.2918206 | E84: 57.22084 | L84: 8.05 | M84: 8.0395486 | N84: 73.115517 | O84: 7.8 | P84: 7.7898732 | Q84: 70.844849 | R84: 7.24 | S84: 7.2306002 | T84: 65.758552 | U84: 4.7051 | V84: 185.23286 | W84: 185 | X84: 121.89
B85: JUL | C85: 6.36 | D85: 6.3164167 | E85: 57.141441 | L85: 8.04 | M85: 7.9849042 | N85: 72.235407 | O85: 0 | P85: 0 | Q85: 0 | R85: 7.59 | S85: 7.5379879 | T85: 68.192381 | U85: 3.8619 | V85: 152.03732 | W85: 184.8 | X85: 126.5
B86: AGO | C86: 6.51 | D86: 6.4239195 | E86: 58.486913 | L86: 8.27 | M86: 8.1606473 | N86: 74.299043 | O86: 7.8 | P86: 7.696862 | Q86: 70.076485 | R86: 7.74 | S86: 7.6376554 | T86: 69.537435 | U86: 3.6436 | V86: 143.44317 | W86: 173.3 | X86: 129
B87: SET | C87: 6.5 | D87: 6.3769253 | E87: 58.322343 | L87: 8.25 | M87: 8.0937899 | N87: 74.024513 | O87: 7.8 | P87: 7.6523104 | Q87: 69.986812 | R87: 7.59 | S87: 7.4462867 | T87: 68.102552 | U87: 3.2841 | V87: 129.29019 | W87: 155.8 | X87: 126.5
B88: OUT | C88: 6.46 | D88: 6.3018242 | E88: 57.836313 | L88: 8.12 | M88: 7.9211784 | N88: 72.698276 | O88: 8.4 | P88: 8.1943225 | Q88: 75.205113 | R88: 7.46 | S88: 7.2773388 | T88: 66.789303 | U88: 2.8339 | V88: 111.56647 | W88: 145.9 | X88: 123.1
B89: NOV | C89: 6.23 | D89: 6.0461957 | E89: 55.620051 | L89: 7.52 | M89: 7.2981366 | N89: 67.136883 | O89: 7.8 | P89: 7.5698758 | Q89: 69.636661 | R89: 7.08 | S89: 6.871118 | T89: 63.208661 | U89: 2.6788 | V89: 105.46041 | W89: 125 | X89: 115.69
B90: DEZ | C90: 5.89 | D90: 5.678203 | E90: 52.12704 | L90: 6.6 | M90: 6.3626723 | N90: 58.410605 | O90: 7.2 | P90: 6.9410971 | Q90: 63.72066 | R90: 6.42 | S90: 6.1891449 | T90: 56.817589 | U90: 2.7513 | V90: 108.31463 | W90: 124 | X90: 103.88
A91: 1997 | B91: JAN | C91: 5.49 | D91: 5.2641672 | E91: 47.832348 | L91: 5.78 | M91: 5.542238 | N91: 50.359012 | O91: 6 | P91: 5.7531882 | Q91: 52.27579 | R91: 6.06 | S91: 5.8107201 | T91: 52.798548 | U91: 2.997318 | V91: 118 | W91: 114 | X91: 96.85
B92: FEV | C92: 5.43 | D92: 5.1748785 | E92: 47.111248 | L92: 5.71 | M92: 5.4417231 | N92: 49.540557 | O92: 6 | P92: 5.7180978 | Q92: 52.056627 | R92: 6.1 | S92: 5.8133994 | T92: 52.924238 | U92: 3.073521 | V92: 121 | W92: 114 | X92: 96.89
B93: MAR | C93: 5.92 | D93: 5.6023469 | E93: 50.771273 | L93: 5.87 | M93: 5.5550298 | N93: 50.342461 | O93: 6 | P93: 5.6780543 | Q93: 51.457371 | R93: 6.2 | S93: 5.8673228 | T93: 53.172617 | U93: 3.327531 | V93: 131 | W93: 120 | X93: 97.79
B94: ABR | C94: 5.97 | D94: 5.6272976 | E94: 50.900883 | L94: 6.2 | M94: 5.8440946 | N94: 52.861888 | O94: 6 | P94: 5.6555755 | Q94: 51.156666 | R94: 6.13 | S94: 5.7781129 | T94: 52.26506 | U94: 3.225927 | V94: 127 | W94: 118 | X94: 96.3
B95: MAI | C95: 5.73 | D95: 5.3636619 | E95: 48.707595 | L95: 6.41 | M95: 6.0001872 | N95: 54.487903 | O95: 6.6 | P95: 6.1780399 | Q95: 56.102989 | R95: 6.09 | S95: 5.7006459 | T95: 51.767758 | U95: 3.073521 | V95: 121 | W95: 116 | X95: 95.01
B96: JUN | C96: 5.84 | D96: 5.4345803 | E96: 49.298819 | L96: 6.2 | M96: 5.7695887 | N96: 52.337788 | O96: 6.6 | P96: 6.1418202 | Q96: 55.714419 | R96: 6.02 | S96: 5.6020845 | T96: 50.818304 | U96: 2.946516 | V96: 116 | W96: 114 | X96: 93.37
B97: JUL | C97: 5.86 | D97: 5.4224114 | E97: 49.424599 | L97: 6.18 | M97: 5.7185158 | N97: 52.123553 | O97: 6 | P97: 5.5519571 | Q97: 50.605392 | R97: 6.39 | S97: 5.9128343 | T97: 53.894742 | U97: 2.667105 | V97: 105 | W97: 108 | X97: 98.55
B98: AGO | C98: 5.82 | D98: 5.3497564 | E98: 49.108773 | L98: 6.5 | M98: 5.9748139 | N98: 54.846568 | O98: 6 | P98: 5.5152128 | Q98: 50.627601 | R98: 6.54 | S98: 6.0115819 | T98: 55.184086 | U98: 2.844912 | V98: 112 | W98: 110 | X98: 100.2
B99: SET | C99: 6.17 | D99: 5.6419166 | E99: 51.756861 | L99: 7.2 | M99: 6.5837601 | N99: 60.396985 | O99: 6.6 | P99: 6.0351134 | Q99: 55.363903 | R99: 7.2 | S99: 6.5837601 | T99: 60.396985 | U99: 2.946516 | V99: 116 | W99: 112 | X99: 109.73
B100: OUT | C100: 6.61 | D100: 6.0085447 | E100: 55.258797 | L100: 7.6 | M100: 6.9084629 | N100: 63.535077 | O100: 6.6060055 | P100: 6.0049136 | Q100: 55.225403 | R100: 8.1 | S100: 7.362967 | T100: 67.715016 | U100: 3.073521 | V100: 121 | W100: 119 | X100: 122.72
B101: NOV | C101: 6.68 | D101: 6.0326921 | E101: 55.384096 | L101: 7.5 | M101: 6.7732322 | N101: 62.182742 | O101: 6.63 | P101: 5.9875373 | Q101: 54.969544 | R101: 8.2 | S101: 7.4054005 | T101: 67.986465 | U101: 3.022719 | V101: 119 | W101: 118 | X101: 123.42
B102: DEZ | C102: 6.79 | D102: 6.097342 | E102: 55.909563 | L102: 7.75 | M102: 6.9594109 | N102: 63.814302 | O102: 6.6594595 | P102: 5.980118 | Q102: 54.834679 | R102: 9 | S102: 8.0818966 | T102: 74.106932 | U102: 2.895714 | V102: 114 | W102: 119 | X102: 134.7
A103: 1998 | B103: JAN | C103: 7.24 | D103: 6.4648629 | E103: 59.095252 | L103: 7.8 | M103: 6.9649076 | N103: 63.666155 | O103: 7.2 | P103: 6.4291455 | Q103: 58.768759 | R103: 8.71 | S103: 7.7774801 | T103: 71.093874 | U103: 2.870313 | V103: 113 | W103: 117 | X103: 129.62
...

Sheet Milho Charts

Sheet Soja
C4: Soja | D4: Soja | E4: Soja | F4: Soja | G4: Soja | H4: Soja | I4: Soja | J4: Soja | K4: Soja | L4: Soja | M4: Soja | N4: Soja | O4: Soja | P4: Soja | Q4: Farelo de soja | R4: Farelo de soja | S4: Farelo de soja | T4: Farelo de soja | U4: Óleo de soja | V4: Óleo de soja | W4: Óleo de soja | X4: Óleo de soja
A5: Ano | B5: Mês | C5: PR | D5: PR | E5: PR | F5: Paranaguá | G5: RS | H5: RS | I5: RS | J5: MT | K5: MT | L5: MT | M5: CBOT | N5: CBOT | O5: CBOT | P5: Prêmio PR | Q5: Atacado SP | R5: Atacado SP | S5: Atacado SP | T5: CBOT | U5: Atacado SP | V5: Atacado SP | W5: Atacado SP | X5: CBOT
C6: R$/60 kg | D6: US$/60 kg | E6: Deflacionado | F6: R$/60 kg | G6: R$/60 kg | H6: US$/60 kg | I6: Deflacionado | J6: R$/60 kg | K6: US$/60 kg | L6: Deflacionado | M6: US$/t | N6: US$/60kg | O6: US$/bushel | P6: US$/bushel | Q6: R$/t | R6: US$/t | S6: Deflacionado | T6: US$/t | U6: R$/t | V6: US$/t | W6: Deflacionado | X6: US$/t
A7: 1990 | B7: JAN | C7: 169.4 | D7: 11.834568 | G7: 165 | H7: 11.527176 | J7: 123.67296 | K7: 8.64 | M7: 207.5 | N7: 12.449794 | O7: 5.6472266 | Q7: 3964 | R7: 276.93168 | T7: 191.31
B8: FEV | C8: 258.75 | D8: 10.935717 | G8: 251.25 | H8: 10.61874 | J8: 199.22562 | K8: 8.42 | M8: 204.1 | N8: 12.245797 | O8: 5.5546937 | Q8: 5325 | R8: 225.05389 | T8: 182.28
B9: MAR | C9: 377.5 | D9: 10.00106 | G9: 365 | H9: 9.6698988 | J9: 283.84992 | K9: 7.52 | M9: 207.5 | N9: 12.449794 | O9: 5.6472266 | Q9: 7850 | R9: 207.96906 | T9: 184.33
B10: ABR | C10: 455 | D10: 9.5156433 | G10: 422.5 | H10: 8.8359545 | J10: 353.8384 | K10: 7.4 | M10: 213.7 | N10: 12.821788 | O10: 5.815963 | Q10: 7750 | R10: 162.07964 | T10: 191.07
B11: MAI | C11: 524 | D11: 10.037737 | G11: 510 | H11: 9.7695535 | J11: 461.47452 | K11: 8.84 | M11: 219.2 | N11: 13.151782 | O11: 5.9656485 | Q11: 9360 | R11: 179.30004 | T11: 200.11
B12: JUN | C12: 538.75 | D12: 9.4234839 | G12: 527.5 | H12: 9.2267058 | J12: 456.79629 | K12: 7.99 | M12: 215.9 | N12: 12.953786 | O12: 5.8758372 | Q12: 9250 | R12: 161.79532 | T12: 192.49
B13: JUL | C13: 615.75 | D13: 9.2436912 | G13: 605 | H13: 9.0823113 | J13: 494.93459 | K13: 7.43 | M13: 219.2 | N13: 13.151782 | O13: 5.9656485 | Q13: 10875 | R13: 163.25642 | T13: 193.98
B14: AGO | C14: 687 | D14: 9.5759806 | G14: 678 | H14: 9.4505311 | J14: 515.82498 | K14: 7.19 | M14: 220.3 | N14: 13.217781 | O14: 5.9955856 | Q14: 11820 | R14: 164.75705 | T14: 192.7
B15: SET | C15: 732.5 | D15: 9.6632059 | G15: 725 | H15: 9.5642653 | J15: 585.95719 | K15: 7.73 | M15: 219.9 | N15: 13.193782 | O15: 5.9846994 | Q15: 13000 | R15: 171.49717 | T15: 198.23
B16: OUT | C16: 950 | D16: 9.9535849 | G16: 944 | H16: 9.8907201 | J16: 640.42253 | K16: 6.71 | M16: 215.5 | N16: 12.929786 | O16: 5.864951 | Q16: 16720 | R16: 175.18309 | T16: 200.77
B17: NOV | C17: 1180 | D17: 9.6816541 | G17: 1171.5 | H17: 9.6119134 | J17: 828.784 | K17: 6.8 | M17: 212.2 | N17: 12.731789 | O17: 5.7751397 | Q17: 23250 | R17: 190.7614 | T17: 192.07
B18: DEZ | C18: 1517.5 | D18: 9.7578384 | G18: 1527.5 | H18: 9.8221405 | J18: 1297.0034 | K18: 8.34 | M18: 210 | N18: 12.599792 | O18: 5.7152655 | Q18: 29000 | R18: 186.47599 | T18: 190.03
A19: 1991 | B19: JAN | C19: 1869 | D19: 8.4900518 | G19: 1847 | H19: 8.3901154 | J19: 1662.057 | K19: 7.55 | M19: 210 | N19: 12.599792 | O19: 5.7152655 | Q19: 36200 | R19: 164.44081 | T19: 180.41
B20: FEV | C20: 2260 | D20: 10.115025 | G20: 2292.5 | H20: 10.260484 | J20: 2004.1671 | K20: 8.97 | M20: 207.5 | N20: 12.449794 | O20: 5.6472266 | Q20: 39937.5 | R20: 178.74726 | T20: 183.56
B21: MAR | C21: 2330 | D21: 9.7518102 | G21: 2392.5 | H21: 10.013393 | J21: 2147.9807 | K21: 8.99 | M21: 211.9 | N21: 12.71379 | O21: 5.766975 | Q21: 36625 | R21: 153.28757 | T21: 184.08
B22: ABR | C22: 2525 | D22: 9.6843478 | G22: 2600 | H22: 9.9720017 | J22: 2247.4926 | K22: 8.62 | M22: 211.9 | N22: 12.71379 | O22: 5.766975 | Q22: 38625 | R22: 148.14176 | T22: 190.39
B23: MAI | C23: 2686 | D23: 9.4344924 | G23: 2735 | H23: 9.6066034 | J23: 2371.551 | K23: 8.33 | M23: 205.2 | N23: 12.311796 | O23: 5.5846308 | Q23: 41050 | R23: 144.18686 | T23: 189.54
B24: JUN | C24: 2992.5 | D24: 9.5842808 | G24: 3055 | H24: 9.7844538 | J24: 2516.5738 | K24: 8.06 | M24: 203.8 | N24: 12.227798 | O24: 5.5465291 | Q24: 46125 | R24: 147.72764 | T24: 190.08
B25: JUL | C25: 3208 | D25: 9.2564273 | G25: 3246 | H25: 9.3660732 | J25: 2755.2315 | K25: 7.95 | M25: 233.5 | N25: 14.009768 | O25: 6.3548309 | Q25: 52300 | R25: 150.90746 | T25: 184.7
B26: AGO | C26: 3910 | D26: 10.426667 | G26: 3985 | H26: 10.626667 | J26: 2876.25 | K26: 7.67 | M26: 207.8 | N26: 12.467794 | O26: 5.6553913 | Q26: 68875 | R26: 183.66667 | T26: 199.18
B27: SET | C27: 4982.5 | D27: 11.323864 | G27: 5190 | H27: 11.795455 | J27: 3832.4 | K27: 8.71 | M27: 207.1 | N27: 12.425794 | O27: 5.6363404 | Q27: 82875 | R27: 188.35227 | T27: 213.29
B28: OUT | C28: 7040.6 | D28: 11.734333 | G28: 7180 | H28: 11.966667 | J28: 6060 | K28: 10.1 | M28: 201.6 | N28: 12.0958 | O28: 5.4866549 | Q28: 122200 | R28: 203.66667 | T28: 203.29
B29: NOV | C29: 7840 | D29: 10.384106 | G29: 8055 | H29: 10.668874 | J29: 6296.7 | K29: 8.34 | M29: 201.2 | N29: 12.0718 | O29: 5.4757686 | Q29: 140250 | R29: 185.76159 | T29: 198.68
B30: DEZ | C30: 9517.5 | D30: 9.7315951 | G30: 10092.5 | H30: 10.31953 | J30: 7462.14 | K30: 7.63 | M30: 200.1 | N30: 12.005801 | O30: 5.4458315 | Q30: 193750 | R30: 198.10838 | T30: 191.3
A31: 1992 | B31: JAN | C31: 12944 | D31: 10.813701 | G31: 12840 | H31: 10.726817 | J31: 8312.4 | K31: 6.9443609 | M31: 203.4 | N31: 12.203798 | O31: 5.5356428 | Q31: 276800 | R31: 231.24478 | T31: 193.29
B32: FEV | C32: 14938.75 | D32: 10.134837 | G32: 15230 | H32: 10.332429 | J32: 13601.52 | K32: 9.2276255 | M32: 205.2 | N32: 12.311796 | O32: 5.5846308 | Q32: 302250 | R32: 205.05427 | T32: 192.7
B33: MAR | C33: 18530 | D33: 10.220629 | G33: 16890 | H33: 9.3160507 | J33: 15282.29 | K33: 8.429283 | M33: 208.2 | N33: 12.491793 | O33: 5.6662775 | Q33: 323500 | R33: 178.43354 | T33: 194.95
B34: ABR | C34: 20850 | D34: 9.4046008 | G34: 20700 | H34: 9.3369418 | J34: 17197.8 | K34: 7.7572395 | M34: 207.8 | N34: 12.467794 | O34: 5.6553913 | Q34: 350000 | R34: 157.871 | T34: 192.53
B35: MAI | C35: 26025 | D35: 10.009615 | G35: 24900 | H35: 9.5769231 | J35: 21598.3 | K35: 8.3070385 | M35: 215.5 | N35: 12.929786 | O35: 5.864951 | Q35: 406525 | R35: 156.35577 | T35: 200.11
B36: JUN | C36: 33337.5 | D36: 9.8051471 | G36: 32050 | H36: 9.4264706 | J36: 29657.3 | K36: 8.7227353 | M36: 218.1 | N36: 13.085784 | O36: 5.9357114 | Q36: 530500 | R36: 156.02941 | T36: 201.31
B37: JUL | C37: 39420 | D37: 10.238961 | G37: 38680 | H37: 10.046753 | J37: 35291.64 | K37: 9.1666597 | M37: 205.2 | N37: 12.311796 | O37: 5.5846308 | Q37: 700600 | R37: 181.97403 | T37: 192.68
B38: AGO | C38: 52325 | D38: 11.252688 | G38: 50837.5 | H38: 10.932796 | J38: 46713.92 | K38: 10.046004 | M38: 198.3 | N38: 11.897803 | O38: 5.3968435 | Q38: 926925 | R38: 199.33871 | T38: 210.19
B39: SET | C39: 71940 | D39: 12.493922 | G39: 71220 | H39: 12.368878 | J39: 64569.89 | K39: 11.213944 | M39: 196.4 | N39: 11.783805 | O39: 5.345134 | Q39: 1313400 | R39: 228.10003 | T39: 195.46
B40: OUT | C40: 85962.5 | D40: 11.695419 | G40: 87487.5 | H40: 11.902899 | J40: 78555.4 | K40: 10.687664 | M40: 193.1 | N40: 11.585808 | O40: 5.2553227 | Q40: 1517400 | R40: 206.44617 | T40: 199.87
B41: NOV | C41: 106900 | D41: 12.048736 | G41: 104587.5 | H41: 11.788093 | J41: 98044.21 | K41: 11.050597 | M41: 196.8 | N41: 11.807805 | O41: 5.3560202 | Q41: 1775591.5 | R41: 200.12753 | T41: 199.13
B42: DEZ | C42: 138212 | D42: 12.503573 | G42: 142468 | H42: 12.888599 | J42: 117011.36 | K42: 10.585623 | M42: 200.5 | N42: 12.029801 | O42: 5.4567178 | Q42: 2278340 | R42: 206.11373 | T42: 204.67
A43: 1993 | B43: JAN | C43: 173262.5 | D43: 12.323781 | G43: 177912.5 | H43: 12.654525 | J43: 149186.72 | K43: 10.611324 | M43: 204.09 | N43: 12.245197 | O43: 5.5544216 | Q43: 2945890.5 | R43: 209.53472 | T43: 203.32
B44: FEV | C44: 194400 | D44: 10.880632 | G44: 206460 | H44: 11.555634 | J44: 171103.51 | K44: 9.5767194 | M44: 204.9 | N44: 12.293797 | O44: 5.5764662 | Q44: 3122500 | R44: 174.76735 | T44: 195.97
B45: MAR | C45: 210880 | D45: 9.2956008 | G45: 214160 | H45: 9.4401834 | J45: 185887.84 | K45: 8.1939452 | M45: 203.8 | N45: 12.227798 | O45: 5.5465291 | Q45: 3404420 | R45: 150.067 | T45: 190.99
B46: ABR | C46: 280475 | D46: 10.055679 | G46: 276887.5 | H46: 9.9270585 | J46: 241084.71 | K46: 8.6434455 | M46: 210.4 | N46: 12.623791 | O46: 5.7261517 | Q46: 4286875 | R46: 153.6944 | T46: 204.27
B47: MAI | C47: 369387.5 | D47: 10.135367 | G47: 367237.5 | H47: 10.076375 | J47: 335925.47 | K47: 9.2172255 | M47: 213.3 | N47: 12.797788 | O47: 5.8050768 | Q47: 5714250 | R47: 156.78933 | T47: 207.11
B48: JUN | C48: 523690 | D48: 11.186372 | G48: 513503 | H48: 10.968771 | J48: 471650.7 | K48: 10.074777 | M48: 216.6 | N48: 12.995785 | O48: 5.8948881 | Q48: 8652600 | R48: 184.82538 | T48: 210.17
B49: JUL | C49: 819975 | D49: 14.1375 | G49: 787875 | H49: 13.584052 | J49: 709841.85 | K49: 12.238653 | M49: 241.2 | N49: 14.471761 | O49: 6.5643906 | Q49: 14355450 | R49: 247.50776 | T49: 250.73
B50: AGO | C50: 1048.17 | D50: 13.648047 | G50: 1020.71 | H50: 13.290495 | J50: 1007.08 | K50: 13.113021 | M50: 240.5 | N50: 14.429761 | O50: 6.5453397 | Q50: 18281.44 | R50: 238.03958 | T50: 239.47
B51: SET | C51: 1364.44 | D51: 11.563051 | G51: 1366.79 | H51: 11.582966 | J51: 1238.71 | K51: 10.497542 | M51: 229.1 | N51: 13.745773 | O51: 6.2350825 | Q51: 23047.3 | R51: 195.3161 | T51: 219.42
B52: OUT | C52: 1859.22 | D52: 12.822207 | G52: 1864.95 | H52: 12.861724 | J52: 1703.01 | K52: 11.744897 | M52: 224.2 | N52: 13.451778 | O52: 6.1017263 | Q52: 31407.13 | R52: 216.6009 | T52: 210.63
B53: NOV | C53: 2565.6 | D53: 12.275598 | G53: 2586.58 | H53: 12.375981 | J53: 2366.71 | K53: 11.323971 | M53: 240.9 | N53: 14.453761 | O53: 6.556226 | Q53: 44516.94 | R53: 212.99971 | T53: 227.13
B54: DEZ | C54: 3596.79 | D54: 13.728206 | G54: 3639.77 | H54: 13.892252 | J54: 3195.73 | K54: 12.197443 | M54: 249.7 | N54: 14.981752 | O54: 6.7957228 | Q54: 56389.15 | R54: 215.22576 | T54: 223.8
A55: 1994 | B55: JAN | C55: 4997.31 | D55: 13.099109 | G55: 5131.69 | H55: 13.45135 | J55: 4413.55 | K55: 11.568938 | M55: 255.3 | N55: 15.317747 | O55: 6.9481299 | Q55: 75111.2 | R55: 196.88388 | T55: 217.13
B56: FEV | C56: 6464.77 | D56: 11.273861 | G56: 6924.92 | H56: 12.076313 | J56: 5786.05 | K56: 10.090246 | M56: 248.1 | N56: 14.885754 | O56: 6.7521779 | Q56: 95945.49 | R56: 167.31857 | T56: 215.17
B57: MAR | C57: 8495.19 | D57: 11.075867 | G57: 8595.93 | H57: 11.20721 | J57: 7671.31 | K57: 10.001708 | M57: 250.6 | N57: 15.035751 | O57: 6.8202168 | Q57: 128603.53 | R57: 167.67083 | T57: 213.49
B58: ABR | C58: 12120.47 | D58: 11.181245 | G58: 9982.06 | H58: 9.2085424 | J58: 9461.66 | K58: 8.7284686 | M58: 242.3 | N58: 14.53776 | O58: 6.5943277 | Q58: 170753.78 | R58: 157.52194 | T58: 207.51
B59: MAI | C59: 17523.14 | D59: 11.232782 | G59: 18126.86 | H59: 11.619782 | J59: 13889.51 | K59: 8.9035321 | M59: 249.7 | N59: 14.981752 | O59: 6.7957228 | Q59: 242932.02 | R59: 155.72565 | T59: 210.18
B60: JUN | C60: 27346.98 | D60: 13.67349 | G60: 28476.65 | H60: 14.238325 | J60: 24818.08 | K60: 12.40904 | M60: 249.3 | N60: 14.957753 | O60: 6.7848366 | Q60: 392887.81 | R60: 196.44391 | T60: 216.98
B61: JUL | C61: 10.5 | D61: 11.290323 | G61: 10.3 | H61: 11.075269 | J61: 9.64 | K61: 10.365591 | M61: 223.1 | N61: 13.385779 | O61: 6.0717892 | Q61: 160.78 | R61: 172.88172 | T61: 199.91
B62: AGO | C62: 10.79 | D62: 12.123596 | G62: 10.64 | H62: 11.955056 | J62: 9.58 | K62: 10.764045 | M62: 213.9 | N62: 12.833788 | O62: 5.8214061 | Q62: 157.29 | R62: 176.73034 | T62: 192.35
B63: SET | C63: 10.9 | D63: 12.778429 | G63: 10.75 | H63: 12.602579 | J63: 9.83 | K63: 11.524033 | M63: 207.2 | N63: 12.431794 | O63: 5.6390619 | Q63: 152.13 | R63: 178.34701 | T63: 186.32
B64: OUT | C64: 10.55 | D64: 12.559524 | G64: 10.49 | H64: 12.488095 | J64: 9.66 | K64: 11.5 | M64: 198.2 | N64: 11.891803 | O64: 5.394122 | Q64: 153.56 | R64: 182.80952 | T64: 179.33
B65: NOV | C65: 10.63 | D65: 12.654762 | G65: 11.24 | H65: 13.380952 | J65: 9.7 | K65: 11.547619 | M65: 204.9 | N65: 12.293797 | O65: 5.5764662 | Q65: 152.85 | R65: 181.96429 | T65: 175.4
B66: DEZ | C66: 10.7 | D66: 12.588235 | G66: 10.49 | H66: 12.341176 | J66: 9.8 | K66: 11.529412 | M66: 206.1 | N66: 12.365795 | O66: 5.6091248 | Q66: 148.07 | R66: 174.2 | T66: 172.92
A67: 1995 | B67: JAN | C67: 11.3 | D67: 13.420428 | E67: 123.81958 | G67: 11.19 | H67: 13.289786 | I67: 122.61426 | J67: 9.8 | K67: 11.638955 | L67: 107.38335 | M67: 202.3 | N67: 12.137799 | O67: 5.5057057 | Q67: 151.22 | R67: 179.5962 | S67: 1656.9909 | T67: 172.61
B68: FEV | C68: 10.97 | D68: 12.883147 | E68: 118.83377 | G68: 11.38 | H68: 13.364651 | I68: 123.27515 | J68: 9.37 | K68: 11.00411 | L68: 101.50159 | M68: 203.4 | N68: 12.203798 | O68: 5.5356428 | Q68: 154.11 | R68: 180.98649 | S68: 1669.4141 | T68: 170.25
B69: MAR | C69: 8.66 | D69: 9.6651786 | E69: 92.139123 | G69: 9.35 | H69: 10.435268 | I69: 99.480461 | J69: 7.34 | K69: 8.1919643 | L69: 78.094822 | M69: 209.1 | N69: 12.545793 | O69: 5.6907715 | Q69: 120.37 | R69: 134.34152 | S69: 1280.6912 | T69: 177.41
B70: ABR | C70: 8.44 | D70: 9.2442497 | E70: 87.777797 | G70: 8.28 | H70: 9.0690033 | I70: 86.113763 | J70: 7.26 | K70: 7.9518072 | L70: 75.505546 | M70: 211.3 | N70: 12.67779 | O70: 5.7506457 | Q70: 116.04 | R70: 127.09748 | S70: 1206.8407 | T70: 184.01
B71: MAI | C71: 8.33 | D71: 9.1942605 | E71: 86.289711 | G71: 8.21 | H71: 9.0618102 | I71: 85.046642 | J71: 7.05 | K71: 7.781457 | L71: 73.030307 | M71: 213.6 | N71: 12.815788 | O71: 5.8132415 | Q71: 117.11 | R71: 129.26049 | S71: 1213.1318 | T71: 185.81
B72: JUN | C72: 9.02 | D72: 9.7830803 | E72: 91.048609 | G72: 8.73 | H72: 9.4685466 | I72: 88.121325 | J72: 7.29 | K72: 7.9067245 | L72: 73.585849 | M72: 216.6 | N72: 12.995785 | O72: 5.8948881 | Q72: 122.12 | R72: 132.45119 | S72: 1232.6891 | T72: 189.85
B73: JUL | C73: 10.71 | D73: 11.442308 | E73: 105.74099 | G73: 10.43 | H73: 11.143162 | I73: 102.97652 | J73: 9 | K73: 9.6153846 | L73: 88.857976 | M73: 226.6 | N73: 13.595775 | O73: 6.1670436 | Q73: 147.45 | R73: 157.53205 | S73: 1455.7898 | T73: 199.86
B74: AGO | C74: 10.92 | D74: 11.48265 | E74: 106.44252 | G74: 10.67 | H74: 11.219769 | I74: 104.00565 | J74: 9.2 | K74: 9.6740273 | L74: 89.676847 | M74: 218.8 | N74: 13.127783 | O74: 5.9547623 | Q74: 153.41 | R74: 161.31441 | S74: 1495.3614 | T74: 194.63
B75: SET | C75: 11.18 | D75: 11.719078 | E75: 110.16783 | G75: 11.12 | H75: 11.656184 | I75: 109.57659 | J75: 9.46 | K75: 9.9161426 | L75: 93.218932 | M75: 234.4 | N75: 14.063767 | O75: 6.3793249 | Q75: 159.44 | R75: 167.12788 | S75: 1571.1233 | T75: 209.82
B76: OUT | C76: 12.01 | D76: 12.485705 | E76: 118.0792 | G76: 11.75 | H76: 12.215407 | I76: 115.52295 | J76: 10.37 | K76: 10.780746 | L76: 101.95514 | M76: 240.8 | N76: 14.447761 | O76: 6.5535044 | Q76: 174.05 | R76: 180.94397 | S76: 1711.2144 | T76: 219.52
B77: NOV | C77: 13.01 | D77: 13.459549 | E77: 126.23565 | G77: 12.87 | H77: 13.314711 | I77: 124.87724 | J77: 11.54 | K77: 11.938754 | L77: 111.97229 | M77: 251.7 | N77: 15.10175 | O77: 6.8501539 | Q77: 200.42 | R77: 207.34533 | S77: 1944.6695 | T77: 230.56
B78: DEZ | C78: 13.69 | D78: 14.077121 | E78: 132.47028 | G78: 13.47 | H78: 13.8509 | I78: 130.34147 | J78: 11.45 | K78: 11.773779 | L78: 110.79509 | M78: 267.2 | N78: 16.031735 | O78: 7.2719949 | Q78: 214.39 | R78: 220.45244 | S78: 2074.5292 | T78: 246.57
A79: 1996 | B79: JAN | C79: 14.53 | D79: 14.91021 | E79: 138.12057 | G79: 14.44 | H79: 14.817855 | I79: 137.26504 | J79: 11.3 | K79: 11.59569 | L79: 107.41655 | M79: 271.86 | N79: 16.31133 | O79: 7.3988194 | Q79: 262.87 | R79: 269.74859 | S79: 2498.8131 | T79: 262.3474
B80: FEV | C80: 12.75 | D80: 12.995617 | E80: 120.28308 | G80: 12.96 | H80: 13.209663 | I80: 122.26421 | J80: 12.18 | K80: 12.414637 | L80: 114.90571 | M80: 267.92 | N80: 16.074934 | O80: 7.2915901 | Q80: 240.56 | R80: 245.19417 | S80: 2269.435 | T80: 254.3447
B81: MAR | C81: 11.72 | D81: 11.885204 | E81: 110.32684 | G81: 12.78 | H81: 12.960146 | I81: 120.30521 | J81: 10.88 | K81: 11.033364 | L81: 102.41946 | M81: 267.8 | N81: 16.067734 | O81: 7.2883243 | Q81: 224.4289 | R81: 227.59243 | S81: 2112.6734 | T81: 253.49593
B82: ABR | C82: 13.14 | D82: 13.270046 | E82: 122.83848 | G82: 13.14 | H82: 13.270046 | I82: 122.83848 | J82: 10.69 | K82: 10.795799 | L82: 99.934804 | M82: 290.03 | N82: 17.401512 | O82: 7.8933259 | Q82: 250.745 | R82: 253.22662 | S82: 2344.0741 | T82: 276.31354
B83: MAI | C83: 13.74 | D83: 13.804883 | E83: 126.32153 | G83: 14.33 | H83: 14.397669 | I83: 131.74581 | J83: 10.69 | K83: 10.74048 | L83: 98.280721 | M83: 296.75 | N83: 17.804706 | O83: 8.0762144 | Q83: 254.14 | R83: 255.3401 | S83: 2336.4885 | T83: 273.01766
B84: JUN | C84: 13.16 | D84: 13.142914 | E84: 119.52798 | G84: 13.82 | H84: 13.802057 | I84: 125.52254 | J84: 10.77 | K84: 10.756017 | L84: 97.820388 | M84: 284.2 | N84: 17.051718 | O84: 7.7346593 | Q84: 254.14 | R84: 253.81005 | S84: 2308.2705 | T84: 263.4497
B85: JUL | C85: 13.68 | D85: 13.586255 | E85: 122.90801 | G85: 14.31 | H85: 14.211938 | I85: 128.56824 | J85: 10.96 | K85: 10.884894 | L85: 98.470157 | M85: 287.57 | N85: 17.253915 | O85: 7.8263757 | Q85: 264.228 | R85: 262.41732 | S85: 2373.9574 | T85: 267.24161
B86: AGO | C86: 15.04 | D86: 14.841129 | E86: 135.12184 | G86: 15.5 | H86: 15.295046 | I86: 139.25455 | J86: 11.77 | K86: 11.614367 | L86: 105.74362 | M86: 290.12 | N86: 17.406912 | O86: 7.8957753 | Q86: 289.3025 | R86: 285.47711 | S86: 2599.1413 | T86: 279.23464
B87: SET | C87: 17.52 | D87: 17.188266 | E87: 157.20115 | G87: 17.72 | H87: 17.38448 | I87: 158.99568 | J87: 14.13 | K87: 13.862455 | L87: 126.7838 | M87: 291.38 | N87: 17.482511 | O87: 7.9300669 | Q87: 329.8 | R87: 323.55538 | S87: 2959.186 | T87: 286.65312
B88: OUT | C88: 17.05 | D88: 16.632524 | E88: 152.64847 | G88: 16.94 | H88: 16.525217 | I88: 151.66365 | J88: 13.81 | K88: 13.471856 | L88: 123.64079 | M88: 255 | N88: 15.299747 | O88: 6.9399652 | Q88: 318.548 | R88: 310.74822 | S88: 2851.957 | T88: 256.59339
B89: NOV | C89: 17.25 | D89: 16.741071 | E89: 154.00415 | G89: 17.45 | H89: 16.935171 | I89: 155.78971 | J89: 14.74 | K89: 14.305124 | L89: 131.59543 | M89: 254 | N89: 15.239748 | O89: 6.9127497 | Q89: 331.9825 | R89: 322.18799 | S89: 2963.8657 | T89: 255.2045
B90: DEZ | C90: 17.09 | D90: 16.475465 | E90: 151.24807 | G90: 17.18 | H90: 16.562229 | I90: 152.04458 | J90: 14.85 | K90: 14.316013 | L90: 131.42386 | M90: 256.87 | N90: 15.411945 | O90: 6.9908583 | Q90: 325.6775 | R90: 313.96655 | S90: 2882.2757 | T90: 250.99371
A91: 1997 | B91: JAN | C91: 15.71 | D91: 15.063765 | E91: 136.87544 | G91: 16.05 | H91: 15.389779 | I91: 139.83774 | J91: 13.15 | K91: 12.609071 | L91: 114.57111 | M91: 266 | N91: 15.959736 | O91: 7.2393363 | Q91: 321.555 | R91: 308.32774 | S91: 2801.5903 | T91: 253.529
B92: FEV | C92: 15.27 | D92: 14.552559 | E92: 132.48412 | G92: 16.76 | H92: 15.972553 | I92: 145.41151 | J92: 12.05 | K92: 11.483846 | L92: 104.54706 | M92: 277 | N92: 16.619725 | O92: 7.5387073 | Q92: 320.53125 | R92: 305.4715 | S92: 2780.9626 | T92: 274.54986
B93: MAR | C93: 15.82 | D93: 14.971137 | E93: 135.67593 | G93: 16.67 | H93: 15.775528 | I93: 142.96573 | J93: 12.14 | K93: 11.488597 | L93: 104.11541 | M93: 301 | N93: 18.059701 | O93: 8.1918805 | Q93: 338 | R93: 319.86373 | S93: 2898.7652 | T93: 300.83972
B94: ABR | C94: 16.53 | D94: 15.58111 | E94: 140.93661 | G94: 17.03 | H94: 16.052408 | I94: 145.19967 | J94: 13 | K94: 12.253747 | L94: 110.83944 | M94: 308 | N94: 18.479694 | O94: 8.3823894 | Q94: 335 | R94: 315.76963 | S94: 2856.2472 | T94: 309.15106
B95: MAI | C95: 17.07 | D95: 15.978658 | E95: 145.10273 | G95: 17.16 | H95: 16.062904 | I95: 145.86777 | J95: 13.73 | K95: 12.852195 | L95: 116.71122 | M95: 316 | N95: 18.959686 | O95: 8.6001138 | Q95: 331 | R95: 309.83806 | S95: 2813.6499 | T95: 331.53877
B96: JUN | C96: 16.67 | D96: 15.512749 | E96: 140.72112 | G96: 16.56 | H96: 15.410385 | I96: 139.79254 | J96: 13.93 | K96: 12.962963 | L96: 117.59119 | M96: 302 | N96: 18.1197 | O96: 8.2190961 | Q96: 319 | R96: 296.85464 | S96: 2692.8636 | T96: 294.8873
B97: JUL | C97: 16.46 | D97: 15.230869 | E97: 138.82746 | G97: 16.54 | H97: 15.304895 | I97: 139.5022 | J97: 13.5 | K97: 12.491903 | L97: 113.86213 | M97: 277 | N97: 16.619725 | O97: 7.5387073 | Q97: 300 | R97: 277.59785 | S97: 2530.2696 | T97: 260.84827
B98: AGO | C98: 17.31 | D98: 15.911389 | E98: 146.06063 | G98: 17.53 | H98: 16.113613 | I98: 147.91698 | J98: 14.78 | K98: 13.585808 | L98: 124.71266 | M98: 269 | N98: 16.139733 | O98: 7.3209829 | Q98: 328.25 | R98: 301.7281 | S98: 2769.7517 | T98: 252.44875
B99: SET | C99: 18.5 | D99: 16.916606 | E99: 155.1867 | G99: 18.5 | H99: 16.916606 | I99: 155.1867 | J99: 15.5 | K99: 14.173372 | L99: 130.02129 | M99: 252 | N99: 15.11975 | O99: 6.8583186 | Q99: 346 | R99: 316.38625 | S99: 2902.4107 | T99: 315.2578
B100: OUT | C100: 19 | D100: 17.271157 | E100: 158.83769 | G100: 19.5 | H100: 17.725661 | I100: 163.01763 | J100: 15.8 | K100: 14.362331 | L100: 132.08608 | M100: 246 | N100: 14.759756 | O100: 6.6950253 | Q100: 339.4 | R100: 308.51741 | S100: 2837.3428 | T100: 239.68411
B101: NOV | C101: 20 | D101: 18.061952 | E101: 165.82065 | G101: 19.75 | H101: 17.836178 | I101: 163.74789 | J101: 16.2 | K101: 14.630182 | L101: 134.31472 | M101: 262 | N101: 15.71974 | O101: 7.1304741 | Q101: 331.75 | R101: 299.60264 | S101: 2750.55 | T101: 261.35533
B102: DEZ | C102: 18.8 | D102: 16.882184 | E102: 154.80115 | G102: 20.6 | H102: 18.498563 | I102: 169.62253 | J102: 17 | K102: 15.265805 | L102: 139.97976 | M102: 252 | N102: 15.11975 | O102: 6.8583186 | Q102: 323.5 | R102: 290.49928 | S102: 2663.7325 | T102: 234.84501
A103: 1998 | B103: JAN | C103: 16 | D103: 14.28699 | E103: 130.59724 | G103: 17.96 | H103: 16.037146 | I103: 146.5954 | J103: 15.5 | K103: 13.840521 | L103: 126.51608 | M103: 246.68 | N103: 14.800555 | O103: 6.7135318 | Q103: 281 | R103: 250.91526 | S103: 2293.6141 | T103: 215.72011
...

Sheet Soja Charts

Sheet Trigo
C4: Trigo | D4: Trigo | E4: Trigo | F4: Trigo | G4: Trigo | H4: Trigo | I4: Trigo | J4: Trigo | K4: Trigo | L4: Trigo
A5: Ano | B5: Mês | C5: PR | D5: PR | E5: PR | F5: PR | G5: RS | H5: RS | I5: RS | J5: Argentina FOB | K5: US SRW | L5: US HRW
C6: R$/60 kg | D6: US$/60 kg | E6: Deflacionado | F6: US$/t | G6: R$/60 kg | H6: US$/60 kg | I6: Deflacionado | J6: US$/t | K6: US$/t | L6: US$/t
A7: 1990 | B7: JAN | C7: 92.89786 | D7: 6.49 | G7: 136.98498 | H7: 9.57 | K7: 163 | L7: 167.92
B8: FEV | C8: 154.26972 | D8: 6.52 | G8: 157.81887 | H8: 6.67 | K8: 155.52 | L8: 160.94
B9: MAR | C9: 245.72646 | D9: 6.51 | G9: 269.50644 | H9: 7.14 | K9: 153.26 | L9: 156.53
B10: ABR | C10: 394.482 | D10: 8.25 | G10: 315.10744 | H10: 6.59 | K10: 150.69 | L10: 159.47
B11: MAI | C11: 448.42377 | D11: 8.59 | G11: 444.24753 | H11: 8.51 | K11: 133.49 | L11: 149.18
B12: JUN | C12: 461.36997 | D12: 8.07 | G12: 451.6509 | H12: 7.9 | K12: 130.49 | L12: 135.58
B13: JUL | C13: 503.59428 | D13: 7.56 | G13: 506.2588 | H13: 7.6 | K13: 119.55 | L13: 124.93
B14: AGO | C14: 566.7618 | D14: 7.9 | G14: 545.2392 | H14: 7.6 | K14: 115.12 | L14: 116.84
B15: SET | C15: 606.424 | D15: 8 | G15: 553.3619 | H15: 7.3 | K15: 108.46 | L15: 114.27
B16: OUT | C16: 733.95667 | D16: 7.69 | G16: 805.53892 | H16: 8.44 | K16: 104.77 | L16: 114.64
B17: NOV | C17: 823.9088 | D17: 6.76 | G17: 893.3804 | H17: 7.33 | K17: 106.37 | L17: 112.8
B18: DEZ | C18: 1049.733 | D18: 6.75 | G18: 1097.943 | H18: 7.06 | K18: 108.35 | L18: 113.17
A19: 1991 | B19: JAN | C19: 1413.2988 | D19: 6.42 | G19: 1523.3688 | H19: 6.92 | K19: 107.07 | L19: 111.33
B20: FEV | C20: 1503.6839 | D20: 6.73 | G20: 1539.4327 | H20: 6.89 | K20: 106.37 | L20: 113.91
B21: MAR | C21: 1651.0063 | D21: 6.91 | G21: 1739.4104 | H21: 7.28 | K21: 116.16 | L21: 119.42
B22: ABR | C22: 1749.4983 | D22: 6.71 | G22: 1726.0326 | H22: 6.62 | K22: 117.05 | L22: 120.89
B23: MAI | C23: 1839.162 | D23: 6.46 | G23: 1861.938 | H23: 6.54 | K23: 115.63 | L23: 121.99
B24: JUN | C24: 1973.2936 | D24: 6.32 | G24: 1985.7828 | H24: 6.36 | K24: 118.18 | L24: 120.15
B25: JUL | C25: 2231.9108 | D25: 6.44 | G25: 2100.2142 | H25: 6.06 | K25: 116.23 | L25: 118.31
B26: AGO | C26: 2306.25 | D26: 6.15 | G26: 2538.75 | H26: 6.77 | K26: 127.06 | L26: 125.3
B27: SET | C27: 2882 | D27: 6.55 | G27: 3018.4 | H27: 6.86 | K27: 137.56 | L27: 135.22
B28: OUT | C28: 3318 | D28: 5.53 | G28: 3714 | H28: 6.19 | K28: 147.2 | L28: 146.97
B29: NOV | C29: 4288.4 | D29: 5.68 | G29: 4431.85 | H29: 5.87 | K29: 147.04 | L29: 149.55
B30: DEZ | C30: 5476.8 | D30: 5.6 | G30: 5750.64 | H30: 5.88 | K30: 157.81 | L30: 160.94
A31: 1992 | B31: JAN | C31: 6439.86 | D31: 5.38 | G31: 7146.09 | H31: 5.97 | K31: 167.26 | L31: 170.12
B32: FEV | C32: 7517.4 | D32: 5.1 | G32: 8195.44 | H32: 5.56 | K32: 170.12 | L32: 177.1
B33: MAR | C33: 11965.8 | D33: 6.6 | G33: 11458.16 | H33: 6.32 | K33: 161.44 | L33: 169.39
B34: ABR | C34: 16472.31 | D34: 7.43 | G34: 14809.56 | H34: 6.68 | K34: 153.07 | L34: 159.83
B35: MAI | C35: 20176 | D35: 7.76 | G35: 19058 | H35: 7.33 | K35: 139.72 | L35: 149.55
B36: JUN | C36: 27744 | D36: 8.16 | G36: 25908 | H36: 7.62 | K36: 140.36 | L36: 148.81
B37: JUL | C37: 30877 | D37: 8.02 | G37: 29606.5 | H37: 7.69 | K37: 129.93 | L37: 136.32
B38: AGO | C38: 36363 | D38: 7.82 | G38: 35944.5 | H38: 7.73 | K38: 118.8 | L38: 128.24
B39: SET | C39: 45200.3 | D39: 7.85 | G39: 44221.44 | H39: 7.68 | K39: 131.47 | L39: 138.89
B40: OUT | C40: 57624.784 | D40: 7.84 | G40: 55860.76 | H40: 7.6 | K40: 137.42 | L40: 140.73
B41: NOV | C41: 68937.771 | D41: 7.77 | G41: 70091.17 | H41: 7.9 | K41: 145.84 | L41: 147.71
B42: DEZ | C42: 89867.394 | D42: 8.13 | G42: 86551.254 | H42: 7.83 | K42: 146.27 | L42: 147.71
A43: 1993 | B43: JAN | C43: 104038.08 | D43: 7.4 | G43: 109380.58 | H43: 7.78 | K43: 156.92 | L43: 155.79
B44: FEV | C44: 136500.9 | D44: 7.64 | G44: 132927.58 | H44: 7.44 | K44: 149.43 | L44: 148.81
B45: MAR | C45: 175589.64 | D45: 7.74 | G45: 164246.64 | H45: 7.24 | K45: 145.46 | L45: 148.08
B46: ABR | C46: 202497.37 | D46: 7.26 | G46: 197476.78 | H46: 7.08 | K46: 156.34 | L46: 141.83
B47: MAI | C47: 273704.95 | D47: 7.51 | G47: 283545.21 | H47: 7.78 | K47: 140.09 | L47: 136.69
B48: JUN | C48: 387628.2 | D48: 8.28 | G48: 363752.55 | H48: 7.77 | K48: 112.25 | L48: 121.99
B49: JUL | C49: 423400 | D49: 7.3 | G49: 418180 | H49: 7.21 | K49: 116.77 | L49: 127.5
B50: AGO | C50: 572.928 | D50: 7.46 | G50: 577.536 | H50: 7.52 | K50: 119.55 | L50: 129.71
B51: SET | C51: 826 | D51: 7 | G51: 862.58 | H51: 7.31 | K51: 115.71 | L51: 131.17
B52: OUT | C52: 983.1 | D52: 6.78 | G52: 1041.1 | H52: 7.18 | K52: 127.87 | L52: 135.95
B53: NOV | C53: 1406.57 | D53: 6.73 | G53: 1414.93 | H53: 6.77 | K53: 136.41 | L53: 146.61
B54: DEZ | C54: 1807.8 | D54: 6.9 | G54: 1805.18 | H54: 6.89 | K54: 140.49 | L54: 158.73
A55: 1994 | B55: JAN | C55: 2617.09 | D55: 6.86 | G55: 2571.31 | H55: 6.74 | K55: 152.71 | L55: 153.22
B56: FEV | C56: 3830.5124 | D56: 6.68 | G56: 3692.8892 | H56: 6.44 | K56: 144.19 | L56: 146.97
B57: MAR | C57: 4916.47 | D57: 6.41 | G57: 4832.1 | H57: 6.3 | K57: 133.49 | L57: 141.1
B58: ABR | C58: 6742.48 | D58: 6.22 | G58: 6840.04 | H58: 6.31 | K58: 129.98 | L58: 140.36
B59: MAI | C59: 10046.4 | D59: 6.44 | G59: 10046.4 | H59: 6.44 | K59: 125.25 | L59: 139.99
B60: JUN | C60: 13160 | D60: 6.58 | G60: 12980 | H60: 6.49 | K60: 120.15 | L60: 139.26
B61: JUL | C61: 6.5751 | D61: 7.07 | G61: 8.3607 | H61: 8.99 | K61: 119.51 | L61: 137.42
B62: AGO | C62: 6.5326 | D62: 7.34 | G62: 7.1289 | H62: 8.01 | K62: 128.15 | L62: 145.87
B63: SET | C63: 7.09696 | D63: 8.32 | G63: 7.09696 | H63: 8.32 | K63: 142.12 | L63: 158.73
B64: OUT | C64: 7.7448 | D64: 9.22 | G64: 7.7448 | H64: 9.22 | K64: 157.38 | L64: 167.18
B65: NOV | C65: 10.1724 | D65: 12.11 | G65: 7.7784 | H65: 9.26 | K65: 152.39 | L65: 162.04
B66: DEZ | C66: 8.3895 | D66: 9.87 | G66: 8.3895 | H66: 9.87 | K66: 157.34 | L66: 164.61
A67: 1995 | B67: JAN | C67: 8.36106 | D67: 9.93 | E67: 91.616189 | G67: 8.36106 | H67: 9.93 | I67: 91.616189 | K67: 152.99 | L67: 156.16
B68: FEV | C68: 8.515 | D68: 10 | E68: 92.239707 | G68: 7.90192 | H68: 9.28 | I68: 85.598448 | K68: 149.71 | L68: 154.32
B69: MAR | C69: 8.44928 | D69: 9.43 | E69: 89.897142 | G69: 8.44928 | H69: 9.43 | I69: 89.897142 | K69: 143.08 | L69: 150.28
B70: ABR | C70: 8.45438 | D70: 9.26 | E70: 87.927352 | G70: 8.45438 | H70: 9.26 | I70: 87.927352 | K70: 140.68 | L70: 148.81
B71: MAI | C71: 8.48922 | D71: 9.37 | E71: 87.939056 | G71: 7.8822 | H71: 8.7 | I71: 81.650991 | K71: 143.28 | L71: 158.73
B72: JUN | C72: 7.87388 | D72: 8.54 | E72: 79.479581 | G72: 7.87388 | H72: 8.54 | I72: 79.479581 | K72: 153.48 | L72: 170.12
B73: JUL | C73: 8.4708 | D73: 9.05 | E73: 83.633127 | G73: 7.26336 | H73: 7.76 | I73: 71.711941 | K73: 173.36 | L73: 190.7
B74: AGO | C74: 8.48292 | D74: 8.92 | E74: 82.687122 | G74: 7.87428 | H74: 8.28 | I74: 76.754414 | K74: 168.47 | L74: 184.45
B75: SET | C75: 8.41428 | D75: 8.82 | E75: 82.914397 | G75: 7.81326 | H75: 8.19 | I75: 76.99194 | K75: 185.61 | L75: 193.64
B76: OUT | C76: 9.022622 | D76: 9.38 | E76: 88.708074 | G76: 7.820247 | H76: 8.13 | I76: 76.886636 | K76: 194.04 | L76: 203.73
B77: NOV | C77: 10.236294 | D77: 10.59 | E77: 99.322465 | G77: 8.428752 | H77: 8.72 | I77: 81.783937 | K77: 198.27 | L77: 203.93
B78: DEZ | C78: 10.25015 | D78: 10.54 | E78: 99.184827 | G78: 9.04425 | H78: 9.3 | I78: 87.516024 | K78: 205.33 | L78: 208.92
A79: 1996 | B79: JAN | C79: 10.203015 | D79: 10.47 | E79: 96.988731 | G79: 9.00438 | H79: 9.24 | I79: 85.594639 | K79: 196.98 | L79: 206.88
B80: FEV | C80: 10.801911 | D80: 11.01 | E80: 101.90487 | G80: 9.604969 | H80: 9.79 | I80: 90.612958 | K80: 203.96 | L80: 218.89
B81: MAR | C81: 11.399316 | D81: 11.56 | E81: 107.30807 | G81: 9.604614 | H81: 9.74 | I81: 90.413545 | K81: 205.51 | L81: 215.32
B82: ABR | C82: 12.001224 | D82: 12.12 | E82: 112.1927 | G82: 10.803082 | H82: 10.91 | I82: 100.99194 | K82: 247.52 | L82: 257.61
B83: MAI | C83: 13.804811 | D83: 13.87 | E83: 126.91738 | G83: 12.003318 | H83: 12.06 | I83: 110.35498 | K83: 213.43 | L83: 262.11
B84: JUN | C84: 14.398694 | D84: 14.38 | E84: 130.77863 | G84: 13.207147 | H84: 13.19 | I84: 119.9562 | K84: 180.6 | L84: 227.34
B85: JUL | C85: 13.854944 | D85: 13.76 | E85: 124.47979 | G85: 13.200459 | H85: 13.11 | I85: 118.59957 | K85: 181.08 | L85: 202.6
B86: AGO | C86: 13.204602 | D86: 13.03 | E86: 118.63232 | G86: 13.802508 | H86: 13.62 | I86: 124.00401 | K86: 174.99 | L86: 191.63
B87: SET | C87: 11.405967 | D87: 11.19 | E87: 102.34196 | G87: 12.608741 | H87: 12.37 | I87: 113.13405 | K87: 169.71 | L87: 178.71
B88: OUT | C88: 10.199745 | D88: 9.95 | E88: 91.318212 | G88: 10.199745 | H88: 9.95 | I88: 91.318212 | K88: 158.44 | L88: 178
B89: NOV | C89: 9.603328 | D89: 9.32 | E89: 85.736371 | G89: 9.603328 | H89: 9.32 | I89: 85.736371 | K89: 158.21 | L89: 176.41
B90: DEZ | C90: 8.40213 | D90: 8.1 | E90: 74.359621 | G90: 8.40213 | H90: 8.1 | I90: 74.359621 | K90: 158.6 | L90: 175.7
A91: 1997 | B91: JAN | C91: 7.800892 | D91: 7.48 | E91: 67.966299 | G91: 7.800892 | H91: 7.48 | I91: 67.966299 | K91: 154.01 | L91: 175.73
B92: FEV | C92: 8.404893 | D92: 8.01 | E92: 72.92173 | G92: 7.198198 | H92: 6.86 | I92: 62.452318 | K92: 143.58 | L92: 172.35
B93: MAR | C93: 9.003084 | D93: 8.52 | E93: 77.212506 | G93: 7.196127 | H93: 6.81 | I93: 61.71563 | K93: 153.8 | L93: 176.61
B94: ABR | C94: 9.601145 | D94: 9.05 | E94: 81.860428 | G94: 8.402328 | H94: 7.92 | I94: 71.639181 | K94: 158.62 | L94: 183.49
B95: MAI | C95: 10.202265 | D95: 9.55 | E95: 86.723872 | G95: 9.604017 | H95: 8.99 | I95: 81.638493 | K95: 152.65 | L95: 172.59
B96: JUN | C96: 10.380636 | D96: 9.66 | E96: 87.628955 | G96: 9.596178 | H96: 8.93 | I96: 81.006892 | K96: 131.59 | L96: 148.39
B97: JUL | C97: 9.596616 | D97: 8.88 | E97: 80.940085 | G97: 9.002231 | H97: 8.33 | I97: 75.926904 | K97: 127.78 | L97: 136.21
B98: AGO | C98: 8.996933 | D98: 8.27 | E98: 75.915523 | G98: 8.996933 | H98: 8.27 | I98: 75.915523 | K98: 140.91 | L98: 150.61
B99: SET | C99: 9.000328 | D99: 8.23 | E99: 75.498983 | G99: 9.000328 | H99: 8.23 | I99: 75.498983 | K99: 143.22 | L99: 151.74
B100: OUT | C100: 8.998818 | D100: 8.18 | E100: 75.229025 | G100: 8.998818 | H100: 8.18 | I100: 75.229025 | K100: 143.65 | L100: 151.59
B101: NOV | C101: 9.002349 | D101: 8.13 | E101: 74.638766 | G101: 8.404407 | H101: 7.59 | I101: 69.68121 | K101: 138.23 | L101: 149.88
B102: DEZ | C102: 8.997888 | D102: 8.08 | E102: 74.089541 | G102: 8.396544 | H102: 7.54 | I102: 69.138013 | K102: 135.74 | L102: 144.62
A103: 1998 | B103: JAN | C103: 9.003996 | D103: 8.04 | E103: 73.493565 | G103: 8.39925 | H103: 7.5 | I103: 68.55743 | K103: 130.21 | L103: 137.1
...

Sheet Trigo Charts

Sheet Cana
C4: Acúcar | D4: Acúcar | E4: Acúcar | F4: Acúcar | G4: Cana | H4: Cana | I4: Cana | J4: Etanol Anidro | K4: Etanol Anidro | L4: Etanol Anidro | M4: Etanol Hidratado Hidratado | N4: Etanol Hidratado Hidratado | O4: Etanol Hidratado Hidratado
A5: Ano | B5: Mês | C5: Atacado SP | D5: Atacado SP | E5: Atacado SP | F5: Futuros ICE NY | G5: SP | H5: SP | I5: SP | J5: FOB usina SP | K5: FOB usina SP | L5: FOB usina SP | M5: FOB usina SP | N5: FOB usina SP | O5: FOB usina SP
C6: R$/50 kg | D6: US$/50 kg | E6: Deflacionado | F6: ¢/libra-peso | G6: R$/t | H6: US$/t | I6: Deflacionado | J6: R$/litro | K6: US$/litro | L6: Deflacionado | M6: R$/litro | N6: US$/litro | O6: Deflacionado
A7: 1990 | B7: JAN | G7: 162.19
B8: FEV | G8: 255.93
B9: MAR | G9: 387.18
B10: ABR | G10: 568.28
B11: MAI | G11: 567.23
B12: JUN | G12: 567.7
B13: JUL | G13: 569.62
B14: AGO | G14: 709.9
B15: SET | G15: 830.69
B16: OUT | G16: 981.53
B17: NOV | G17: 1291.62
B18: DEZ | G18: 1435.77
A19: 1991 | B19: JAN | G19: 1651.55
B20: FEV | G20: 2493.88
B21: MAR | G21: 2472.33
B22: ABR | G22: 2564.27
B23: MAI | G23: 2578.11
B24: JUN | G24: 2715.66
B25: JUL | G25: 3090.94
B26: AGO | G26: 3382.72
B27: SET | G27: 3757.82
B28: OUT | G28: 5324.49
B29: NOV | G29: 6382.79
B30: DEZ | G30: 8719.44
A31: 1992 | B31: JAN | G31: 10889.19
B32: FEV | G32: 13605.17
B33: MAR | G33: 17518.8
B34: ABR | G34: 19664.79
B35: MAI | G35: 24333.63
B36: JUN | G36: 30355.81
B37: JUL | G37: 38876.64
B38: AGO | G38: 48269.66
B39: SET | G39: 60105
B40: OUT | G40: 75052
B41: NOV | G41: 78850
B42: DEZ | G42: 95668
A43: 1993 | B43: JAN | G43: 106484
B44: FEV | G44: 173431
B45: MAR | G45: 200118
B46: ABR | G46: 260368
B47: MAI | G47: 348353
B48: JUN | G48: 444876
B49: JUL | G49: 594200
B50: AGO | G50: 815.63
B51: SET | G51: 1065.88
B52: OUT | G52: 1392.24
B53: NOV | G53: 2153.17
B54: DEZ | G54: 2892.2
A55: 1994 | B55: JAN | G55: 4005.98
B56: FEV | G56: 6076.02
B57: MAR | G57: 8305.65
B58: ABR | G58: 11881.69
B59: MAI | G59: 16958.87
B60: JUN | G60: 24722.7
B61: JUL | G61: 10.87
B62: AGO | G62: 10.77
B63: SET | G63: 10.74
B64: OUT | G64: 10.69
B65: NOV | G65: 10.72
B66: DEZ | G66: 10.82
A67: 1995 | B67: JAN | G67: 10.78
B68: FEV | G68: 10.66
B69: MAR | G69: 10.69
B70: ABR | G70: 10.75
B71: MAI | G71: 11.2
B72: JUN | G72: 11.45
B73: JUL | G73: 11.57
B74: AGO | G74: 11.89
B75: SET | G75: 11.84
B76: OUT | G76: 12.48
B77: NOV | G77: 12.77
B78: DEZ | G78: 12.88
A79: 1996 | B79: JAN | G79: 12.92
B80: FEV | G80: 13.03
B81: MAR | G81: 12.97
B82: ABR | G82: 14.16
B83: MAI | G83: 14.73
B84: JUN | G84: 14.77
B85: JUL | G85: 14.82
B86: AGO | G86: 14.8
B87: SET | G87: 14.91
B88: OUT | G88: 15.15
B89: NOV | G89: 14.89
B90: DEZ | G90: 14.89
A91: 1997 | B91: JAN | G91: 15
B92: FEV | G92: 14.93
B93: MAR | G93: 14.87
B94: ABR | G94: 14.96
B95: MAI | G95: 15.05
B96: JUN | G96: 15.84
B97: JUL | G97: 16
B98: AGO | G98: 15.98
B99: SET | G99: 15.34
B100: OUT | G100: 15.5
B101: NOV | G101: 15.85
B102: DEZ | G102: 16.68
A103: 1998 | B103: JAN | G103: 16.24
...

Sheet Cana Charts
B35: PREÇOS FOB USINAS - SÃO PAULO
B36: ANO-SAFRA | C36: ETANOL ANIDRO | E36: ETANOL HIDRATADO
C37: R$/LITRO | D37: US$/LITRO | E37: R$/LITRO | F37: US$/LITRO
B38: MÉDIA 2020/2021 | C38: =AVERAGE(Cana!J370:J381) -> 2.1749083 | D38: =AVERAGE(Cana!K370:K381) -> 0.40191807 | E38: =AVERAGE(Cana!M370:M381) -> 1.9054083 | F38: =AVERAGE(Cana!N370:N381) -> 0.35201233
B39: MÉDIA 2021/2022 | C39: =AVERAGE(Cana!J382:J393) -> 3.6412 | D39: =AVERAGE(Cana!K382:K393) -> 0.68268734 | E39: =AVERAGE(Cana!M382:M393) -> 3.15505 | F39: =AVERAGE(Cana!N382:N393) -> 0.59153672
B40: MÉDIA 2022/2023 | C40: =AVERAGE(Cana!J394:J405) -> 3.3288333 | D40: =AVERAGE(Cana!K394:K405) -> 0.64827058 | E40: =AVERAGE(Cana!M394:M405) -> 2.8881083 | F40: =AVERAGE(Cana!N394:N405) -> 0.56276154
B41: MÉDIA 2023/2024 | C41: =AVERAGE(Cana!J406:J416) -> 2.6098 | D41: =AVERAGE(Cana!K406:K416) -> 0.52939763 | E41: =AVERAGE(Cana!M406:M416) -> 2.2690909 | F41: =AVERAGE(Cana!N406:N416) -> 0.46012882
B42: MÉDIA 2024/2025 | C42: =AVERAGE(Cana!J417:J429) -> 2.8921231 | D42: =AVERAGE(Cana!K417:K429) -> 0.51420544 | E42: =AVERAGE(Cana!M417:M429) -> 2.5525385 | F42: =AVERAGE(Cana!N417:N429) -> 0.45377963
B43: MÉDIA 2025/2026 | C43: =AVERAGE(Cana!J430:J441) -> 3.19395 | D43: =AVERAGE(Cana!K430:K441) -> 0.58835357 | E43: =AVERAGE(Cana!M430:M441) -> 2.793725 | F43: =AVERAGE(Cana!N430:N441) -> 0.51472102
B44: MÉDIA 2026/2027 | C44: =AVERAGE(Cana!J442:J443) -> 2.785 | D44: =AVERAGE(Cana!K442:K443) -> 0.5565773 | E44: =AVERAGE(Cana!M442:M443) -> 2.4246 | F44: =AVERAGE(Cana!N442:N443) -> 0.48454495
B45: VAR. 30 DIAS (%) | C45: 0 | D45: -0.0076923077 | E45: 0.14419924 | F45: 0.13539771
B46: VAR. 12 MESES (%) | C46: -0.20496894 | D46: -0.18356426 | E46: -0.061090909 | F46: -0.035812587
B49: ETHANOL AVERAGE PRICES - FOB SÃO PAULO PLANTS
B50: HARVEST | C50: ANHYDROUS ETHANOL | E50: HYDROUS ETHANOL
C51: R$/l | D51: U$/l | E51: R$/l | F51: U$/l
B52: 2019/2020 | C52: =#REF! -> #REF! | D52: =#REF! -> #REF! | E52: =#REF! -> #REF! | F52: =#REF! -> #REF!
B53: 2020/2021 | C53: =C38 -> 2.1749083 | D53: =D38 -> 0.40191807 | E53: =E38 -> 1.9054083 | F53: =F38 -> 0.35201233
B54: 2021/2022 | C54: =C39 -> 3.6412 | D54: =D39 -> 0.68268734 | E54: =E39 -> 3.15505 | F54: =F39 -> 0.59153672
B55: 2022/2023 | C55: =C40 -> 3.3288333 | D55: =D40 -> 0.64827058 | E55: =E40 -> 2.8881083 | F55: =F40 -> 0.56276154
B56: 2023/2024 | C56: =C41 -> 2.6098 | D56: =D41 -> 0.52939763 | E56: =E41 -> 2.2690909 | F56: =F41 -> 0.46012882
B57: 2024/2025 | C57: =C42 -> 2.8921231 | D57: =D42 -> 0.51420544 | E57: =E42 -> 2.5525385 | F57: =F42 -> 0.45377963
B58: 2025/2026 | C58: =C43 -> 3.19395 | D58: =D43 -> 0.58835357 | E58: =E43 -> 2.793725 | F58: =F43 -> 0.51472102
B59: 30 DAYS CHANGE | C59: =C45 -> 0 | D59: =D45 -> -0.0076923077 | E59: =E45 -> 0.14419924 | F59: =F45 -> 0.13539771
B60: 12 MO CHANGE | C60: =C46 -> -0.20496894 | D60: =D46 -> -0.18356426 | E60: =E46 -> -0.061090909 | F60: =F46 -> -0.035812587

Sheet Demais AGRÍCOLAS
C4: Café Arábica | D4: Café Arábica | E4: Café Arábica | F4: Café Arábica | G4: Café Robusta | H4: Café Robusta | I4: Café Robusta | J4: Feijão | K4: Feijão | L4: Feijão | M4: Laranja | N4: Laranja | O4: Laranja | P4: Laranja | Q4: Laranja | R4: Laranja
A5: Ano | B5: Mês | C5: SP | D5: SP | E5: SP | F5: Futuros ICE NY | G5: ES | H5: ES | I5: ES | J5: Cores SP | K5: Cores SP | L5: Cores SP | M5: Indústria SP | N5: Indústria SP | O5: Indústria SP | P5: Mesa SP | Q5: Mesa SP | R5: Mesa SP
C6: R$/60 kg | D6: US$/60 kg | E6: Deflacionado | F6: ¢/libra-peso | G6: R$/60 kg | H6: US$/60 kg | I6: Deflacionado | J6: R$/60 kg | K6: US$/60 kg | L6: Deflacionado | M6: R$/40,8 kg | N6: US$/40,8 kg | O6: Deflacionado | P6: R$/40,8 kg | Q6: US$/40,8 kg | R6: Deflacionado
A7: 1990 | B7: JAN | C7: 1381.301 | D7: 96.5 | F7: 80.65 | J7: 404.15 | K7: 28.234596
B8: FEV | C8: 2247.795 | D8: 95 | F8: 85.64 | J8: 538.95 | K8: 22.777989
B9: MAR | C9: 3170.664 | D9: 84 | F9: 94.64 | J9: 1121.26 | K9: 29.705399
B10: ABR | C10: 4030.8888 | D10: 84.3 | F10: 94.83 | J10: 1201.28 | K10: 25.122971
B11: MAI | C11: 4218.0024 | D11: 80.8 | F11: 94.39 | J11: 1596.4 | K11: 30.580618
B12: JUN | C12: 4236.3711 | D12: 74.1 | F12: 89.13 | J12: 1960.21 | K12: 34.286789
B13: JUL | C13: 4323.1837 | D13: 64.9 | F13: 87.7 | J13: 2222.48 | K13: 33.364058
B14: AGO | C14: 5775.231 | D14: 80.5 | F14: 95.07 | J14: 2312.11 | K14: 32.228123
B15: SET | C15: 5942.9552 | D15: 78.4 | F15: 97.05 | J15: 2322.75 | K15: 30.641927
B16: OUT | C16: 5965.1875 | D16: 62.5 | F16: 92.41 | J16: 2773.65 | K16: 29.060801
B17: NOV | C17: 6179.316 | D17: 50.7 | F17: 84.58 | J17: 3267.58 | K17: 26.809813
B18: DEZ | C18: 7977.9708 | D18: 51.3 | F18: 91.4 | J18: 3307 | K18: 21.264693
A19: 1991 | B19: JAN | C19: 11799.504 | D19: 53.6 | F19: 87.05 | J19: 4293.31 | K19: 19.502635
B20: FEV | C20: 14187.805 | D20: 63.5 | F20: 88.22 | J20: 5292.44 | K20: 23.68724
B21: MAR | C21: 16103.882 | D21: 67.4 | F21: 93.54 | J21: 5967.77 | K21: 24.977064
B22: ABR | C22: 17077.815 | D22: 65.5 | F22: 90.91 | J22: 8359 | K22: 32.059985
B23: MAI | C23: 16968.12 | D23: 59.6 | F23: 88.08 | J23: 10422.6 | K23: 36.609062
B24: JUN | C24: 18015.671 | D24: 57.7 | F24: 85.35 | J24: 11254.8 | K24: 36.046504
B25: JUL | C25: 18922.722 | D25: 54.6 | F25: 83.68 | J25: 11682 | K25: 33.707476
B26: AGO | C26: 19125 | D26: 51 | F26: 81.52 | J26: 9857.4 | K26: 26.2864
B27: SET | C27: 25432 | D27: 57.8 | F27: 89.88 | J27: 10122.6 | K27: 23.005909
B28: OUT | C28: 30720 | D28: 51.2 | F28: 81.56 | J28: 13957.2 | K28: 23.262
B29: NOV | C29: 36844 | D29: 48.8 | F29: 78.57 | J29: 14869.2 | K29: 19.694305
B30: DEZ | C30: 44205.6 | D30: 45.2 | F30: 79.7 | J30: 16318.8 | K30: 16.68589
A31: 1992 | B31: JAN | C31: 55421.1 | D31: 46.3 | F31: 77.38 | J31: 22853.4 | K31: 19.092231
B32: FEV | C32: 66035.2 | D32: 44.8 | F32: 68.81 | J32: 28166.4 | K32: 19.10882
B33: MAR | C33: 84123.2 | D33: 46.4 | F33: 71.86 | J33: 35218.8 | K33: 19.425703
B34: ABR | C34: 101095.2 | D34: 45.6 | F34: 66.43 | J34: 41796.6 | K34: 18.852774
B35: MAI | C35: 109200 | D35: 42 | F35: 63.02 | J35: 49600.8 | K35: 19.077231
B36: JUN | C36: 137360 | D36: 40.4 | F36: 59.64 | J36: 54648 | K36: 16.072941
B37: JUL | C37: 154000 | D37: 40 | F37: 60.16 | J37: 69353.4 | K37: 18.01387
B38: AGO | C38: 182280 | D38: 39.2 | F38: 52.5 | J38: 99448.8 | K38: 21.386839
B39: SET | C39: 238957 | D39: 41.5 | F39: 54.16 | J39: 151363.8 | K39: 26.287565
B40: OUT | C40: 378530.15 | D40: 51.5 | F40: 63.16 | J40: 197884.2 | K40: 26.922654
B41: NOV | C41: 528789.08 | D41: 59.6 | F41: 67.8 | J41: 259608 | K41: 29.260507
B42: DEZ | C42: 822402.72 | D42: 74.4 | F42: 78.37 | J42: 270187.2 | K42: 24.442925
A43: 1993 | B43: JAN | C43: 970084.8 | D43: 69 | F43: 66.55 | J43: 292074 | K43: 20.774582
B44: FEV | C44: 1130956.4 | D44: 63.3 | F44: 62.54 | J44: 306543 | K44: 17.157312
B45: MAR | C45: 1431486.6 | D45: 63.1 | F45: 61.67 | J45: 525820.2 | K45: 23.17818
B46: ABR | C46: 1414134.5 | D46: 50.7 | F46: 55.96 | J46: 859041.6 | K46: 30.798632
B47: MAI | C47: 1909739 | D47: 52.4 | F47: 61.43 | J47: 1128014 | K47: 30.950792
B48: JUN | C48: 2565462 | D48: 54.8 | F48: 60.4 | J48: 1348274 | K48: 28.800043
B49: JUL | C49: 3625000 | D49: 62.5 | F49: 71.3 | J49: 1406036 | K49: 24.242
B50: AGO | C50: 5429.76 | D50: 70.7 | F50: 74.59 | J50: 1864.2 | K50: 24.273438
B51: SET | C51: 8649.4 | D51: 73.3 | F51: 79.91 | J51: 2769 | K51: 23.466102
B52: OUT | C52: 10048.5 | D52: 69.3 | F52: 75.41 | J52: 3913.8 | K52: 26.991724
B53: NOV | C53: 14818.1 | D53: 70.9 | F53: 75.84 | J53: 5710.8 | K53: 27.324402
B54: DEZ | C54: 18549.6 | D54: 70.8 | F54: 77.2 | J54: 8361.6 | K54: 31.914504
A55: 1994 | B55: JAN | C55: 26514.25 | D55: 69.5 | F55: 73.39 | J55: 12088.2 | K55: 31.685976
B56: FEV | C56: 44784.883 | D56: 78.1 | F56: 75.55 | J56: 27037.8 | K56: 47.151004
B57: MAR | C57: 60593 | D57: 79 | F57: 80.53 | J57: 47993.4 | K57: 62.572881
B58: ABR | C58: 102438 | D58: 94.5 | F58: 83.39 | J58: 61494.6 | K58: 56.729336
B59: MAI | C59: 189696 | D59: 121.6 | F59: 115.63 | J59: 47317.2 | K59: 30.331538
B60: JUN | C60: 258200 | D60: 129.1 | F60: 138.78 | J60: 56402.4 | K60: 28.2012
B61: JUL | C61: 187.767 | D61: 201.9 | F61: 216.81 | J61: 30.71 | K61: 33.021505
B62: AGO | C62: 165.807 | D62: 186.3 | F62: 184.97 | J62: 29.97 | K62: 33.674157
B63: SET | C63: 176.571 | D63: 207 | F63: 219.7 | J63: 29.37 | K63: 34.431419
B64: OUT | C64: 165.144 | D64: 196.6 | F64: 196.29 | J64: 43.27 | K64: 51.511905
B65: NOV | C65: 149.688 | D65: 178.2 | F65: 172.88 | J65: 40.6 | K65: 48.333333
B66: DEZ | C66: 127.16 | D66: 149.6 | F66: 164.14 | J66: 26.09 | K66: 30.694118
A67: 1995 | B67: JAN | C67: 136.5724 | D67: 162.2 | E67: 1496.49 | F67: 168.97 | J67: 25.75 | K67: 30.581948
B68: FEV | C68: 135.2182 | D68: 158.8 | E68: 1464.7666 | F68: 162.87 | J68: 25.23 | K68: 29.630065
B69: MAR | C69: 146.4064 | D69: 163.4 | E69: 1557.7087 | F69: 174.78 | J69: 25.41 | K69: 28.359375
B70: ABR | C70: 143.341 | D70: 157 | E70: 1490.7769 | F70: 168.24 | J70: 24.25 | K70: 26.560789
B71: MAI | C71: 145.866 | D71: 161 | E71: 1511.0126 | F71: 166.29 | J71: 22.08 | K71: 24.370861
B72: JUN | C72: 137.1014 | D72: 148.7 | E72: 1383.9126 | F72: 148.41 | J72: 20.59 | K72: 22.331887
B73: JUL | C73: 126.828 | D73: 135.5 | E73: 1252.1866 | F73: 139.93 | J73: 19.88 | K73: 21.239316
B74: AGO | C74: 135.4224 | D74: 142.4 | E74: 1320.0276 | F74: 147.24 | J74: 19.48 | K74: 20.483701
B75: SET | C75: 127.0728 | D75: 133.2 | E75: 1252.1766 | F75: 127.7 | J75: 19.92 | K75: 20.880503
B76: OUT | C76: 121.10321 | D76: 125.9 | E76: 1190.6553 | F76: 121.99 | J76: 20.29 | K76: 21.093669
B77: NOV | C77: 123.91812 | D77: 128.2 | E77: 1202.3739 | F77: 138.46 | J77: 21.05 | K77: 21.777364
B78: DEZ | C78: 117.18625 | D78: 120.5 | E78: 1133.9442 | F78: 101.02 | J78: 27.53 | K78: 28.308483
A79: 1996 | B79: JAN | C79: 121.0329 | D79: 124.2 | E79: 1150.5253 | F79: 106.18 | J79: 30.74 | K79: 31.544382
B80: FEV | C80: 142.35761 | D80: 145.1 | E80: 1342.997 | F80: 121.39 | J80: 26.75 | K80: 27.265314
B81: MAR | C81: 141.20952 | D81: 143.2 | E81: 1329.2833 | F81: 116.8 | J81: 29.75 | K81: 30.169354
B82: ABR | C82: 132.78582 | D82: 134.1 | E82: 1241.34 | F82: 119.58 | J82: 30.98 | K82: 31.286609
B83: MAI | C83: 139.64059 | D83: 140.3 | E83: 1283.8146 | F83: 128.06 | J83: 32.41 | K83: 32.563046
B84: JUN | C84: 130.76978 | D84: 130.6 | E84: 1187.7391 | F84: 119.46 | J84: 37.12 | K84: 37.071807
B85: JUL | C85: 107.83899 | D85: 107.1 | E85: 968.87977 | F85: 109.69 | J85: 38.06 | K85: 37.799186
B86: AGO | C86: 98.90784 | D86: 97.6 | E86: 888.60433 | F86: 120.78 | J86: 38.13 | K86: 37.625814
B87: SET | C87: 110.0844 | D87: 108 | E87: 987.7508 | F87: 108.3 | J87: 40.4 | K87: 39.635044
B88: OUT | C88: 111.42837 | D88: 108.7 | E88: 997.61705 | F88: 113.98 | J88: 49.71 | K88: 48.49283
B89: NOV | C89: 110.97408 | D89: 107.7 | E89: 990.75184 | F89: 119.98 | J89: 40.16 | K89: 38.975155
B90: DEZ | C90: 111.50975 | D90: 107.5 | E90: 986.87151 | F90: 109.13 | J90: 28.22 | K90: 27.205244
A91: 1997 | B91: JAN | C91: 134.6 | D91: 129.06319 | E91: 1172.7202 | F91: 127.26 | J91: 27.61 | K91: 26.474254
B92: FEV | C92: 171.25 | D92: 163.20404 | E92: 1485.7829 | F92: 171.16 | J92: 27.98 | K92: 26.665396
B93: MAR | C93: 190.87 | D93: 180.62837 | E93: 1636.9447 | F93: 184.09 | J93: 28.63 | K93: 27.093783
B94: ABR | C94: 194.24 | D94: 183.08983 | E94: 1656.1118 | F94: 254.03 | J94: 31.13 | K94: 29.343011
B95: MAI | C95: 209.34 | D95: 195.95619 | E95: 1779.4848 | F95: 123.71 | J95: 34.26 | K95: 32.069643
B96: JUN | C96: 216.08 | D96: 201.07947 | E96: 1824.0563 | F96: 213.1 | J96: 31.57 | K96: 29.378373
B97: JUL | C97: 177.02 | D97: 163.80124 | E97: 1493.0277 | F97: 171.64 | J97: 25.1 | K97: 23.225687
B98: AGO | C98: 186.16711 | D98: 171.12521 | E98: 1570.8657 | F98: 186.86 | J98: 22.83 | K98: 20.985385
B99: SET | C99: 190.08 | D99: 173.81127 | E99: 1594.4804 | F99: 175.89 | J99: 23.11 | K99: 21.132041
B100: OUT | C100: 177.89 | D100: 161.70348 | E100: 1487.1388 | F100: 157.83 | J100: 24.98 | K100: 22.707027
B101: NOV | C101: 183.13 | D101: 165.38427 | E101: 1518.3367 | F101: 157.27 | J101: 21.72 | K101: 19.61528
B102: DEZ | C102: 194.6 | D102: 174.74856 | E102: 1602.3566 | F102: 168.9 | J102: 20.91 | K102: 18.77694
A103: 1998 | B103: JAN | C103: 213.68 | D103: 190.80275 | E103: 1744.1262 | F103: 170.06 | J103: 25.6 | K103: 22.859184
...

Sheet Demais AGRÍCOLAS Charts

Sheet PECUÁRIA
C4: Bezerro | D4: Bezerro | E4: Bezerro | F4: Boi Gordo | G4: Boi Gordo | H4: Boi Gordo | I4: Beef | J4: Frango vivo | K4: Frango vivo | L4: Frango vivo | M4: Frango vivo | N4: Frango Resfriado | O4: Frango Resfriado | P4: Frango Resfriado | Q4: Chicken Meat | R4: Suíno vivo | S4: Suíno vivo | T4: Suíno vivo | U4: Suíno vivo | V4: Suíno Carcaça | W4: Suíno Carcaça | X4: Suíno Carcaça | Y4: Ovos Brancos | Z4: Ovos Brancos | AA4: Ovos Brancos | AB4: Tilápia | AC4: Tilápia | AD4: Tilápia
A5: Ano | B5: Mês | C5: MS | D5: MS | E5: MS | F5: SP | G5: SP | H5: SP | J5: SP | K5: SP | L5: SP | M5: Custo Produção | N5: Atacado SP | O5: Atacado SP | P5: Atacado SP | R5: SC | S5: SC | T5: SC | U5: Custo Produção | V5: SP | W5: SP | X5: SP | Y5: Atacado SP | Z5: Atacado SP | AA5: Atacado SP | AB5: Norte PR | AC5: Norte PR | AD5: Norte PR
C6: R$/un | D6: US$/un | E6: Deflacionado | F6: R$/@ | G6: Deflacionado | H6: US$/@ | I6: US$/kg | J6: R$/kg | K6: US$/kg | L6: Deflacionado | M6: R$/kg | N6: R$/kg | O6: US$/kg | P6: Deflacionado | Q6: US$/kg | R6: R$/kg | S6: US$/kg | T6: Deflacionado | U6: R$/kg | V6: R$/kg | W6: US$/kg | X6: Deflacionado | Y6: R$/cx. 30 dz. | Z6: US$/cx. 30 dz. | AA6: Deflacionado | AB6: R$/kg | AC6: US$/kg | AD6: Deflacionado
A7: 1990 | B7: JAN | F7: 0 | I7: 2.7847 | J7: 11.88062 | K7: 0.83 | Q7: 1.0544697 | R7: 12.816703 | S7: 0.89539631
B8: FEV | F8: 0 | I8: 2.4573 | J8: 20.58507 | K8: 0.87 | Q8: 1.0714453 | R8: 20.65199 | S8: 0.8728283
B9: MAR | F9: 0 | I9: 2.4839 | J9: 42.27552 | K9: 1.12 | Q9: 1.1098057 | R9: 36.27762 | S9: 0.9610984
B10: ABR | F10: 0 | I10: 2.472 | J10: 35.862 | K10: 0.75 | Q10: 1.081807 | R10: 32.963065 | S10: 0.68937313
B11: MAI | F11: 0 | I11: 2.48 | J11: 38.10819 | K11: 0.73 | Q11: 1.0809252 | R11: 50.659438 | S11: 0.97043154
B12: JUN | F12: 0 | I12: 2.504 | J12: 49.16706 | K12: 0.86 | Q12: 1.1082625 | R12: 57.630092 | S12: 1.0080302
B13: JUL | F13: 0 | I13: 2.5589 | J13: 57.95331 | K13: 0.87 | Q13: 1.1034123 | R13: 78.421624 | S13: 1.1772721
B14: AGO | F14: 0 | I14: 2.6541 | J14: 65.28522 | K14: 0.91 | Q14: 1.0961371 | R14: 81.09453 | S14: 1.1303634
B15: SET | F15: 0 | I15: 2.6969 | J15: 85.65739 | K15: 1.13 | Q15: 1.0930506 | R15: 86.084111 | S15: 1.1356293
B16: OUT | F16: 0 | I16: 2.5851 | J16: 88.76199 | K16: 0.93 | Q16: 1.0729886 | R16: 70.3 | S16: 0.73656528
B17: NOV | F17: 0 | I17: 2.5342 | J17: 80.4408 | K17: 0.66 | Q17: 1.0657133 | R17: 78.53 | S17: 0.64432228
B18: DEZ | F18: 0 | I18: 2.5477 | J18: 90.19928 | K18: 0.58 | Q18: 1.0471945 | R18: 83.531531 | S18: 0.537125
A19: 1991 | B19: JAN | F19: 0 | I19: 2.5931 | J19: 138.6882 | K19: 0.63 | Q19: 1.0513833 | R19: 118.72209 | S19: 0.53930266
B20: FEV | F20: 0 | I20: 2.7269 | J20: 185.4469 | K20: 0.83 | Q20: 1.0754136 | R20: 151.02857 | S20: 0.67595473
B21: MAR | F21: 0 | I21: 2.5918 | J21: 164.8617 | K21: 0.69 | Q21: 1.0696816 | R21: 201.43694 | S21: 0.84307933
B22: ABR | F22: 0 | I22: 2.6112 | J22: 153.8307 | K22: 0.59 | Q22: 1.056013 | R22: 210.0982 | S22: 0.80580755
B23: MAI | F23: 0 | I23: 2.6259 | J23: 179.361 | K23: 0.63 | Q23: 1.0648315 | R23: 221.57209 | S23: 0.77826516
B24: JUN | F24: 0 | I24: 2.7029 | J24: 196.7049 | K24: 0.63 | Q24: 1.0471945 | R24: 225.03252 | S24: 0.72072676
B25: JUL | F25: 0 | I25: 2.6874 | J25: 218.3391 | K25: 0.63 | Q25: 1.0714453 | R25: 252.14767 | S25: 0.72755192
B26: AGO | F26: 0 | I26: 2.6411 | J26: 225 | K26: 0.6 | Q26: 1.0471945 | R26: 274.44747 | S26: 0.73185993
B27: SET | F27: 0 | I27: 2.7448 | J27: 255.2 | K27: 0.58 | Q27: 1.0471945 | R27: 295.19748 | S27: 0.67090337
B28: OUT | F28: 0 | I28: 2.7198 | J28: 348 | K28: 0.58 | Q28: 1.061745 | R28: 340.71465 | S28: 0.56785775
B29: NOV | F29: 0 | I29: 2.7073 | J29: 460.55 | K29: 0.61 | Q29: 1.0392579 | R29: 472.79732 | S29: 0.62622162
B30: DEZ | F30: 0 | I30: 2.6081 | J30: 557.46 | K30: 0.57 | Q30: 1.0416829 | R30: 538.20402 | S30: 0.55031086
A31: 1992 | B31: JAN | F31: 0 | I31: 2.5715 | J31: 670.32 | K31: 0.56 | Q31: 1.0538084 | R31: 603 | S31: 0.5037594
B32: FEV | F32: 0 | I32: 2.5241 | J32: 869.66 | K32: 0.59 | Q32: 1.0255892 | R32: 844 | S32: 0.57259159
B33: MAR | F33: 0 | I33: 2.4493 | J33: 870.24 | K33: 0.48 | Q33: 1.0392579 | R33: 1015 | S33: 0.55984556
B34: ABR | F34: 0 | I34: 2.3847 | J34: 908.97 | K34: 0.41 | Q34: 1.0368328 | R34: 1125 | S34: 0.50744249
B35: MAI | F35: 0 | I35: 2.3766 | J35: 1378 | K35: 0.53 | Q35: 1.0377146 | R35: 1321 | S35: 0.50807692
B36: JUN | F36: 0 | I36: 2.3347 | J36: 1802 | K36: 0.53 | Q36: 1.0480763 | R36: 1805 | S36: 0.53088235
B37: JUL | F37: 0 | I37: 2.3457 | J37: 1848 | K37: 0.48 | Q37: 1.0648315 | R37: 2113 | S37: 0.54883117
B38: AGO | F38: 0 | I38: 2.4454 | J38: 2511 | K38: 0.54 | Q38: 1.0769569 | R38: 2698 | S38: 0.58021505
B39: SET | F39: 0 | I39: 2.4403 | J39: 3397.22 | K39: 0.59 | Q39: 1.0778387 | R39: 3583 | S39: 0.62226468
B40: OUT | F40: 0 | I40: 2.5003 | J40: 4483.561 | K40: 0.61 | Q40: 1.056013 | R40: 4288 | S40: 0.58339342
B41: NOV | F41: 0 | I41: 2.5406 | J41: 5323.38 | K41: 0.6 | Q41: 1.0866572 | R41: 5272 | S41: 0.59420894
B42: DEZ | F42: 0 | I42: 2.5417 | J42: 7406.046 | K42: 0.67 | Q42: 1.0857754 | R42: 9257 | S42: 0.83744956
A43: 1993 | B43: JAN | F43: 0 | I43: 2.3545 | J43: 8857.296 | K43: 0.63 | Q43: 1.1128922 | R43: 11504 | S43: 0.81825424
B44: FEV | F44: 0 | I44: 2.3876 | J44: 10362.634 | K44: 0.58 | Q44: 1.1254585 | R44: 13742 | S44: 0.76914423
B45: MAR | F45: 0 | I45: 2.5263 | J45: 12931.02 | K45: 0.57 | Q45: 1.1503707 | R45: 16848 | S45: 0.74266067
B46: ABR | F46: 0 | I46: 2.5922 | J46: 15061.788 | K46: 0.54 | Q46: 1.1796922 | R46: 20339 | S46: 0.72920028
B47: MAI | F47: 0 | I47: 2.6762 | J47: 17493.792 | K47: 0.48 | Q47: 1.2418624 | R47: 23764 | S47: 0.65204388
B48: JUN | F48: 0 | I48: 2.7425 | J48: 23547.945 | K48: 0.503 | Q48: 1.233044 | R48: 32642 | S48: 0.69725515
B49: JUL | F49: 0 | I49: 2.8197 | J49: 33640 | K49: 0.58 | Q49: 1.2500195 | R49: 46411 | S49: 0.80018966
B50: AGO | F50: 0 | I50: 2.8043 | J50: 49.4592 | K50: 0.644 | Q50: 1.2771364 | R50: 55.296 | S50: 0.72
B51: SET | F51: 0 | I51: 2.7337 | J51: 75.874 | K51: 0.643 | Q51: 1.2694202 | R51: 85.096154 | S51: 0.72115385
B52: OUT | F52: 0 | I52: 2.6698 | J52: 89.32 | K52: 0.616 | Q52: 1.227312 | R52: 110 | S52: 0.75862069
B53: NOV | F53: 0 | I53: 2.6411 | J53: 122.892 | K53: 0.588 | Q53: 1.2143047 | R53: 174.65285 | S53: 0.83565955
B54: DEZ | F54: 0 | I54: 2.4626 | J54: 167.156 | K54: 0.638 | Q54: 1.1832196 | R54: 239.12698 | S54: 0.91269841
A55: 1994 | B55: JAN | F55: 0 | I55: 2.4216 | J55: 241.871 | K55: 0.634 | Q55: 1.1640394 | R55: 262.9933 | S55: 0.68936645
B56: FEV | F56: 0 | I56: 2.4936 | J56: 328.00196 | K56: 0.572 | Q56: 1.1823377 | R56: 441.05038 | S56: 0.76914423
B57: MAR | F57: 0 | I57: 2.6903 | J57: 460.2 | K57: 0.6 | Q57: 1.2224618 | R57: 569.62074 | S57: 0.74266067
B58: ABR | F58: 0 | I58: 2.6277 | J58: 598.368 | K58: 0.552 | Q58: 1.2345872 | R58: 743.7218 | S58: 0.68609023
B59: MAI | F59: 0 | I59: 2.3907 | J59: 859.56 | K59: 0.551 | Q59: 1.299403 | R59: 1019.6078 | S59: 0.65359477
B60: JUN | F60: 0 | I60: 2.2324 | J60: 996 | K60: 0.498 | Q60: 1.308442 | R60: 1260 | S60: 0.63
B61: JUL | F61: 0 | I61: 2.1912 | J61: 0.85 | K61: 0.91397849 | Q61: 1.2782387 | R61: 0.570834 | S61: 0.6138
B62: AGO | F62: 0 | I62: 2.1995 | J62: 0.8 | K62: 0.8988764 | Q62: 1.2321621 | R62: 0.71597765 | S62: 0.80446927
B63: SET | F63: 0 | I63: 2.2081 | J63: 0.85 | K63: 0.996483 | Q63: 1.2374532 | R63: 0.90317647 | S63: 1.0588235
B64: OUT | F64: 0 | I64: 2.1248 | J64: 0.95 | K64: 1.1309524 | Q64: 1.19777 | R64: 0.92894118 | S64: 1.1058824
B65: NOV | F65: 0 | I65: 2.1887 | J65: 0.99 | K65: 1.1785714 | Q65: 1.1391272 | R65: 1 | S65: 1.1904762
B66: DEZ | F66: 0 | I66: 2.2256 | J66: 0.97 | K66: 1.1411765 | Q66: 1.1298678 | R66: 1.0008065 | S66: 1.1774194
A67: 1995 | B67: JAN | F67: 0 | I67: 2.1278992 | J67: 0.87 | K67: 1.0332542 | Q67: 1.1298678 | R67: 1.1160327 | S67: 1.3254545
B68: FEV | F68: 0 | I68: 2.1616299 | J68: 0.78 | K68: 0.91603053 | Q68: 1.1340565 | R68: 0.95368 | S68: 1.12
B69: MAR | F69: 0 | I69: 2.0441237 | J69: 0.75 | K69: 0.83705357 | Q69: 1.1430955 | R69: 0.7616 | S69: 0.85
B70: ABR | F70: 0 | I70: 1.9233105 | J70: 0.75 | K70: 0.82146769 | Q70: 1.1327338 | R70: 0.77605 | S70: 0.85
B71: MAI | F71: 0 | I71: 1.7520115 | J71: 0.75 | K71: 0.82781457 | Q71: 1.1536776 | R71: 0.7701 | S71: 0.85
B72: JUN | F72: 0 | I72: 1.6605198 | J72: 0.77 | K72: 0.835141 | Q72: 1.1929199 | R72: 0.79292 | S72: 0.86
B73: JUL | F73: 0 | I73: 1.6331825 | J73: 0.82 | K73: 0.87606838 | Q73: 1.2434057 | R73: 0.7488 | S73: 0.8
B74: AGO | F74: 0 | I74: 1.6865343 | J74: 0.8 | K74: 0.84121977 | Q74: 1.3110875 | R74: 0.71325 | S74: 0.75
B75: SET | F75: 0 | I75: 1.7647983 | J75: 0.74 | K75: 0.77568134 | Q75: 1.3366611 | R75: 0.6678 | S75: 0.7
B76: OUT | F76: 0 | I76: 1.8223389 | J76: 0.76 | K76: 0.79010292 | Q76: 1.2945529 | R76: 0.654092 | S76: 0.68
B77: NOV | F77: 0 | I77: 1.9376405 | J77: 0.79 | K77: 0.81729774 | Q77: 1.3150558 | R77: 0.67662 | S77: 0.7
B78: DEZ | F78: 0 | I78: 1.9098623 | J78: 0.79 | K78: 0.81233933 | Q78: 1.2912459 | R78: 0.7002 | S78: 0.72
A79: 1996 | B79: JAN | F79: 0 | I79: 1.8629039 | J79: 0.79 | K79: 0.81067214 | Q79: 1.2886004 | R79: 0.68215 | S79: 0.7
B80: FEV | F80: 0 | I80: 1.8124181 | J80: 0.79 | K80: 0.80521863 | Q80: 1.2528855 | R80: 0.68677 | S80: 0.7
B81: MAR | F81: 0 | I81: 1.7200445 | J81: 0.79 | K81: 0.80113579 | Q81: 1.2151865 | R81: 0.69027 | S81: 0.7
B82: ABR | F82: 0 | I82: 1.7151944 | J82: 0.82 | K82: 0.82811553 | Q82: 1.2350281 | R82: 0.69314 | S82: 0.7
B83: MAI | F83: 0 | I83: 1.7015257 | J83: 0.84 | K83: 0.84396664 | Q83: 1.3298268 | R83: 0.676804 | S83: 0.68
B84: JUN | F84: 0 | I84: 1.6541264 | J84: 0.84 | K84: 0.83890942 | Q84: 1.4250664 | R84: 0.690897 | S84: 0.69
B85: JUL | F85: 0 | I85: 1.6841092 | J85: 0.83 | K85: 0.82431225 | Q85: 1.4607812 | R85: 0.735037 | S85: 0.73
B86: AGO | F86: 0 | I86: 1.7553184 | J86: 0.85 | K86: 0.83876061 | Q86: 1.4704815 | R86: 0.76005 | S86: 0.75
B87: SET | F87: 0 | I87: 1.7453977 | J87: 0.88 | K87: 0.86333758 | Q87: 1.4704815 | R87: 0.81544 | S87: 0.8
B88: OUT | F88: 0 | I88: 1.7938993 | J88: 0.89 | K88: 0.86820798 | Q88: 1.4479944 | R88: 0.799578 | S88: 0.78
B89: NOV | F89: 0 | I89: 1.7672234 | J89: 0.87 | K89: 0.8443323 | Q89: 1.4513013 | R89: 0.82432 | S89: 0.8
B90: DEZ | F90: 0 | I90: 1.7872854 | J90: 0.84 | K90: 0.80979466 | Q90: 1.4371918 | R90: 0.93357 | S90: 0.9
A91: 1997 | B91: JAN | F91: 23.43 | I91: 1.7652392 | J91: 0.84 | K91: 0.80544635 | Q91: 1.415366 | R91: 0.88 | S91: 0.84380094
B92: FEV | F92: 24.06 | I92: 1.8386531 | J92: 0.84 | K92: 0.80053369 | Q92: 1.3787693 | R92: 0.93 | S92: 0.88630516
B93: MAR | F93: 24.73 | I93: 2.0403758 | J93: 0.82 | K93: 0.77600076 | Q93: 1.3628961 | R93: 1.05 | S93: 0.99365951
B94: ABR | F94: 25.78 | I94: 1.9976062 | J94: 0.81 | K94: 0.76350269 | Q94: 1.3514321 | R94: 1.09 | S94: 1.0274295
B95: MAI | F95: 25.21 | I95: 1.8975164 | J95: 0.82 | K95: 0.76757465 | Q95: 1.3423931 | R95: 0.98 | S95: 0.91734531
B96: JUN | F96: 25.16 | I96: 1.7564208 | J96: 0.85 | K96: 0.790992 | Q96: 1.3423931 | R96: 0.95 | S96: 0.88404988
B97: JUL | F97: 25.92 | I97: 1.8022768 | J97: 0.85 | K97: 0.78652725 | Q97: 1.3514321 | R97: 0.93 | S97: 0.86055335
B98: AGO | F98: 26.12 | I98: 1.8386531 | J98: 0.86 | K98: 0.79051383 | Q98: 1.3825172 | R98: 0.92 | S98: 0.84566596
B99: SET | F99: 25.62 | I99: 1.7888287 | J99: 0.84 | K99: 0.76810534 | Q99: 1.3900129 | R99: 0.91 | S99: 0.83211412
B100: OUT | F100: 26.75 | I100: 1.7645778 | J100: 0.84 | K100: 0.76356695 | Q100: 1.3146149 | R100: 0.91 | S100: 0.82719753
B101: NOV | F101: 26.84 | I101: 1.8346848 | J101: 0.84 | K101: 0.758602 | Q101: 1.2689793 | R101: 0.91 | S101: 0.82181884
B102: DEZ | F102: 26.94 | I102: 1.8529831 | J102: 0.84 | K102: 0.75431034 | Q102: 1.2341463 | R102: 0.9 | S102: 0.80818966
A103: 1998 | B103: JAN | F103: 26.86 | I103: 1.8150636 | J103: 0.91 | K103: 0.81257255 | Q103: 1.2235641 | R103: 0.89 | S103: 0.79471381
...

Sheet PECUÁRIA Charts
R18: CARNES: EVOLUÇÃO DOS PREÇOS PAGOS AOS CRIADORES
R19: PERÍODO | S19: BOI GORDO | T19: FRANGO VIVO | U19: SUÍNO VIVO
R20: ÚLTIMOS 30 DIAS | S20: 0.041509434 | T20: 0.0042194093 | U20: 0.10805085
R21: ACUMULADO 2026 | S21: 0.11245466 | T21: -0.13296903 | U21: -0.37214886
R22: ÚLTIMOS 12 MESES | S22: 0.1737765 | T22: -0.13924051 | U22: -0.36759371

Sheet Leite
C4: LEITE | D4: LEITE | E4: LEITE | F4: LEITE | G4: LEITE | H4: LEITE | I4: LEITE | J4: LEITE | K4: LEITE | L4: LEITE | M4: LEITE | N4: LEITE | O4: LEITE | P4: LEITE | Q4: LEITE | R4: LEITE | S4: LEITE | T4: LEITE | U4: LEITE | V4: LEITE | W4: LEITE
A5: Ano | B5: Mês | C5: BRASIL | D5: BRASIL | E5: BRASIL | F5: GO | G5: GO | H5: GO | I5: MG | J5: MG | K5: MG | L5: PR | M5: PR | N5: PR | O5: RS | P5: RS | Q5: RS | R5: SC | S5: SC | T5: SC | U5: SP | V5: SP | W5: SP
C6: R$/litro | D6: US$/litro | E6: Deflacionado | F6: R$/litro | G6: US$/litro | H6: Deflacionado | I6: R$/litro | J6: US$/litro | K6: Deflacionado | L6: R$/litro | M6: US$/litro | N6: Deflacionado | O6: R$/litro | P6: US$/litro | Q6: Deflacionado | R6: R$/litro | S6: US$/litro | T6: Deflacionado | U6: R$/litro | V6: US$/litro | W6: Deflacionado
A7: 1990 | B7: JAN
B8: FEV
B9: MAR
B10: ABR
B11: MAI
B12: JUN
B13: JUL
B14: AGO
B15: SET
B16: OUT
B17: NOV
B18: DEZ
A19: 1991 | B19: JAN
B20: FEV
B21: MAR
B22: ABR
B23: MAI
B24: JUN
B25: JUL
B26: AGO
B27: SET
B28: OUT
B29: NOV
B30: DEZ
A31: 1992 | B31: JAN
B32: FEV
B33: MAR
B34: ABR
B35: MAI
B36: JUN
B37: JUL
B38: AGO
B39: SET
B40: OUT
B41: NOV
B42: DEZ
A43: 1993 | B43: JAN
B44: FEV
B45: MAR
B46: ABR
B47: MAI
B48: JUN
B49: JUL
B50: AGO
B51: SET
B52: OUT
B53: NOV
B54: DEZ
A55: 1994 | B55: JAN
B56: FEV
B57: MAR
B58: ABR
B59: MAI
B60: JUN
B61: JUL
B62: AGO
B63: SET
B64: OUT
B65: NOV
B66: DEZ
A67: 1995 | B67: JAN
B68: FEV
B69: MAR
B70: ABR
B71: MAI
B72: JUN
B73: JUL
B74: AGO
B75: SET
B76: OUT
B77: NOV
B78: DEZ
A79: 1996 | B79: JAN
B80: FEV
B81: MAR
B82: ABR
B83: MAI
B84: JUN
B85: JUL
B86: AGO
B87: SET
B88: OUT
B89: NOV
B90: DEZ
A91: 1997 | B91: JAN
B92: FEV
B93: MAR
B94: ABR
B95: MAI
B96: JUN
B97: JUL
B98: AGO
B99: SET
B100: OUT
B101: NOV
B102: DEZ
A103: 1998 | B103: JAN
...

Sheet Leite Charts

Sheet Indicadores
C4: BRENT OIL | D4: NATURAL GAS | E4: DIESEL S-10 | F4: DIESEL S-10 | G4: DIESEL S-10 | H4: ETANOL | I4: ETANOL | J4: ETANOL | K4: GASOLINA C | L4: GASOLINA C | M4: GASOLINA C | N4: USD
A5: Ano | B5: Mês | C5: GLOBAL | D5: EUROPE | E5: VAREJO BR | F5: VAREJO BR | G5: VAREJO BR | H5: VAREJO BR | I5: VAREJO BR | J5: VAREJO BR | K5: VAREJO BR | L5: VAREJO BR | M5: VAREJO BR | N5: COMERCIAL
C6: US$/barril | D6: US$/mmbtu | E6: R$/litro | F6: U$/litro | G6: Deflacionado | H6: R$/litro | I6: U$/litro | J6: Deflacionado | K6: R$/litro | L6: U$/litro | M6: Deflacionado | N6: R$/US$
A7: 1990 | B7: JAN | C7: 20.95 | D7: 2.82 | N7: 14.314
B8: FEV | C8: 19.9 | D8: 2.82 | N8: 23.661
B9: MAR | C9: 18.45 | D9: 2.82 | N9: 37.746
B10: ABR | C10: 16.75 | D10: 2.82 | N10: 47.816
B11: MAI | C11: 16.7 | D11: 2.82 | N11: 52.203
B12: JUN | C12: 15.7 | D12: 2.82 | N12: 57.171
B13: JUL | C13: 17.55 | D13: 2.82 | N13: 66.613
B14: AGO | C14: 27.05 | D14: 2.82 | N14: 71.742
B15: SET | C15: 34.1 | D15: 2.82 | N15: 75.803
B16: OUT | C16: 36.05 | D16: 2.82 | N16: 95.443
B17: NOV | C17: 33 | D17: 2.82 | N17: 121.88
B18: DEZ | C18: 28 | D18: 2.82 | N18: 155.516
A19: 1991 | B19: JAN | C19: 23.65 | D19: 3.44 | N19: 220.14
B20: FEV | C20: 19.4 | D20: 3.41 | N20: 223.43
B21: MAR | C21: 19.45 | D21: 3.33 | N21: 238.93
B22: ABR | C22: 19.25 | D22: 3.47 | N22: 260.73
B23: MAI | C23: 19.3 | D23: 3.37 | N23: 284.7
B24: JUN | C24: 18.2 | D24: 3.29 | N24: 312.23
B25: JUL | C25: 19.45 | D25: 3 | N25: 346.57
B26: AGO | C26: 19.75 | D26: 2.98 | N26: 375
B27: SET | C27: 20.5 | D27: 2.97 | N27: 440
B28: OUT | C28: 22.2 | D28: 2.71 | N28: 600
B29: NOV | C29: 21.25 | D29: 2.7 | N29: 755
B30: DEZ | C30: 18.4 | D30: 2.7 | N30: 978
A31: 1992 | B31: JAN | C31: 18.15 | D31: 2.57 | N31: 1197
B32: FEV | C32: 18.1 | D32: 2.5 | N32: 1474
B33: MAR | C33: 17.6 | D33: 2.58 | N33: 1813
B34: ABR | C34: 18.95 | D34: 2.47 | N34: 2217
B35: MAI | C35: 19.9 | D35: 2.49 | N35: 2600
B36: JUN | C36: 21.15 | D36: 2.5 | N36: 3400
B37: JUL | C37: 20.25 | D37: 2.55 | N37: 3850
B38: AGO | C38: 19.75 | D38: 2.56 | N38: 4650
B39: SET | C39: 20.25 | D39: 2.57 | N39: 5758
B40: OUT | C40: 20.3 | D40: 2.63 | N40: 7350.1
B41: NOV | C41: 19.2 | D41: 2.64 | N41: 8872.3
B42: DEZ | C42: 18.15 | D42: 2.64 | N42: 11053.8
A43: 1993 | B43: JAN | C43: 17.4 | D43: 2.76 | N43: 14059.2
B44: FEV | C44: 18.45 | D44: 2.74 | N44: 17866.61
B45: MAR | C45: 18.75 | D45: 2.75 | N45: 22686
B46: ABR | C46: 18.65 | D46: 2.68 | N46: 27892.2
B47: MAI | C47: 18.5 | D47: 2.68 | N47: 36445.4
B48: JUN | C48: 17.65 | D48: 2.68 | N48: 46815
B49: JUL | C49: 16.8 | D49: 2.66 | N49: 58000
B50: AGO | C50: 16.7 | D50: 2.65 | N50: 76.8
B51: SET | C51: 16 | D51: 2.62 | N51: 118
B52: OUT | C52: 16.6 | D52: 2.62 | N52: 145
B53: NOV | C53: 15.15 | D53: 2.62 | N53: 209
B54: DEZ | C54: 13.6 | D54: 2.6 | N54: 262
A55: 1994 | B55: JAN | C55: 14.25 | D55: 2.47 | N55: 381.5
B56: FEV | C56: 13.8 | D56: 2.36 | N56: 573.43
B57: MAR | C57: 13.95 | D57: 2.36 | N57: 767
B58: ABR | C58: 15.15 | D58: 2.36 | N58: 1084
B59: MAI | C59: 16.2 | D59: 2.36 | N59: 1560
B60: JUN | C60: 16.75 | D60: 2.36 | N60: 2000
B61: JUL | C61: 17.6 | D61: 2.42 | N61: 0.93
B62: AGO | C62: 16.8 | D62: 2.46 | N62: 0.89
B63: SET | C63: 15.9 | D63: 2.48 | N63: 0.853
B64: OUT | C64: 16.4 | D64: 2.56 | N64: 0.84
B65: NOV | C65: 17.2 | D65: 2.57 | N65: 0.84
B66: DEZ | C66: 15.96 | D66: 2.56 | N66: 0.85
A67: 1995 | B67: JAN | C67: 16.63 | D67: 2.66 | N67: 0.842
B68: FEV | C68: 17.08 | D68: 2.66 | N68: 0.8515
B69: MAR | C69: 17.01 | D69: 2.65 | N69: 0.896
B70: ABR | C70: 18.67 | D70: 2.71 | N70: 0.913
B71: MAI | C71: 18.38 | D71: 2.71 | N71: 0.906
B72: JUN | C72: 17.35 | D72: 2.73 | N72: 0.922
B73: JUL | C73: 15.86 | D73: 2.8 | N73: 0.936
B74: AGO | C74: 16.07 | D74: 2.8 | N74: 0.951
B75: SET | C75: 16.78 | D75: 2.78 | N75: 0.954
B76: OUT | C76: 16.12 | D76: 2.75 | N76: 0.9619
B77: NOV | C77: 16.88 | D77: 2.75 | N77: 0.9666
B78: DEZ | C78: 17.96 | D78: 2.73 | N78: 0.9725
A79: 1996 | B79: JAN | C79: 17.94 | D79: 2.75 | N79: 0.9745
B80: FEV | C80: 17.97 | D80: 2.77 | N80: 0.9811
B81: MAR | C81: 19.99 | D81: 2.67 | N81: 0.9861
B82: ABR | C82: 21.01 | D82: 3.1 | N82: 0.9902
B83: MAI | C83: 19.12 | D83: 2.81 | N83: 0.9953
B84: JUN | C84: 18.27 | D84: 2.81 | N84: 1.0013
B85: JUL | C85: 19.61 | D85: 2.78 | N85: 1.0069
B86: AGO | C86: 20.58 | D86: 2.79 | N86: 1.0134
B87: SET | C87: 22.59 | D87: 2.79 | N87: 1.0193
B88: OUT | C88: 24.18 | D88: 2.94 | N88: 1.0251
B89: NOV | C89: 22.64 | D89: 2.96 | N89: 1.0304
B90: DEZ | C90: 23.9 | D90: 2.96 | N90: 1.0373
A91: 1997 | B91: JAN | C91: 23.47 | D91: 2.89 | N91: 1.0429
B92: FEV | C92: 20.83 | D92: 2.89 | N92: 1.0493
B93: MAR | C93: 19.21 | D93: 2.83 | N93: 1.0567
B94: ABR | C94: 17.47 | D94: 2.77 | N94: 1.0609
B95: MAI | C95: 19.1425 | D95: 2.74 | N95: 1.0683
B96: JUN | C96: 17.55 | D96: 2.76 | N96: 1.0746
B97: JUL | C97: 18.4 | D97: 2.67 | N97: 1.0807
B98: AGO | C98: 18.71 | D98: 2.67 | N98: 1.0879
B99: SET | C99: 18.45 | D99: 2.7 | N99: 1.0936
B100: OUT | C100: 19.85 | D100: 2.63 | N100: 1.1001
B101: NOV | C101: 19 | D101: 2.66 | N101: 1.1073
B102: DEZ | C102: 17 | D102: 2.65 | N102: 1.1136
A103: 1998 | B103: JAN | C103: 15.09 | D103: 2.65 | N103: 1.1199
...

Sheet XAxis
B2: JAN | C2: JAN | D2: 1990
B3: FEV | C3: FEB | D3: 1991
B4: MAR | C4: MAR | D4: 1992
B5: ABR | C5: APR | D5: 1993
B6: MAI | C6: MAY | D6: 1994
B7: JUN | C7: JUN | D7: 1995
B8: JUL | C8: JUL | D8: 1996
B9: AGO | C9: AUG | D9: 1997
B10: SET | C10: SEP | D10: 1998
B11: OUT | C11: OCT | D11: 1999
B12: NOV | C12: NOV | D12: 2000
B13: DEZ | C13: DEC | D13: 2001
D14: 2002
D15: 2003
D16: 2004
D17: 2005
D18: 2006
D19: 2007
D20: 2008
D21: 2009
D22: 2010
D23: 2011
D24: 2012
D25: 2013
... D34: 2022
